<?xml version="1.0" encoding="utf-8" ?>
<Defs>
	<KCSG.StructureLayoutDef>
		<defName>AM_SanguophageCamp_Alpha</defName>
		<spawnConduits>false</spawnConduits>
		<layouts>
			<li>
				<li>.,.,.,.,.,.,.,.,.,.,ChunkSlate,.,.,.,.,.,.,.,.,.,.,.,.,.,.,.,.</li>
				<li>.,.,.,.,.,.,.,.,.,.,.,.,.,.,.,.,.,.,.,.,.,.,.,.,.,.,.</li>
				<li>.,.,.,.,.,.,.,.,.,.,.,.,.,.,ChunkSlate,.,.,.,.,.,ChunkSlate,.,.,.,.,.,.</li>
				<li>.,.,.,.,.,ChunkSlate,.,Slate,Slate,Slate,.,.,.,Slate,Slate,.,.,.,.,.,.,.,.,.,.,.,.</li>
				<li>.,.,.,.,.,.,.,Slate,Slate,Slate,Slate,Slate,.,Slate,Slate,Slate,Slate,Slate,Slate,.,.,.,.,.,.,.,.</li>
				<li>.,.,.,.,.,.,.,Slate,Slate,Slate,Slate,Slate,Filth_RubbleRock,Slate,Slate,Slate,Slate,Slate,Slate,.,ChunkSlate,.,.,.,.,.,.</li>
				<li>.,.,.,.,.,Slate,Slate,Slate,Slate,Slate,Slate,Slate,Door_BlocksSlate,Slate,Slate,Slate,Slate,Slate,Slate,Slate,Slate,Slate,.,.,.,.,.</li>
				<li>.,.,.,.,.,Slate,Slate,Slate,Slate,.,.,.,.,.,.,Wall_BlocksSlate,Wall_BlocksSlate,Slate,Slate,Slate,Slate,Slate,.,.,.,.,.</li>
				<li>.,.,.,.,.,.,.,Slate,Slate,Bed_WoodLog_Kemetic_East,.,.,.,.,.,Wall_BlocksSlate,Wall_BlocksSlate,Slate,Slate,Slate,.,ChunkSlate,.,.,.,.,.</li>
				<li>.,.,.,ChunkSlate,.,.,.,Slate,Slate,EndTable_WoodLog_Kemetic_East,.,.,.,DiningChair_WoodLog_Kemetic_East,Table1x2c_WoodLog_Morbid_North,Wall_BlocksSlate,Wall_BlocksSlate,Wall_BlocksSlate,Slate,Slate,Slate,Slate,Slate,.,ChunkSlate,.,.</li>
				<li>.,.,Slate,Slate,Slate,Slate,Slate,Slate,Slate,Bed_WoodLog_Kemetic_East,.,.,.,DiningChair_WoodLog_Kemetic_East,.,Wall_BlocksSlate,.,Wall_BlocksSlate,Slate,Slate,Slate,Slate,Slate,.,.,.,.</li>
				<li>ChunkSlate,.,Slate,Slate,Slate,Slate,Slate,Slate,Slate,EndTable_WoodLog_Kemetic_East,.,.,AM_RaidSpawner,.,.,Door_BlocksSlate,ChunkSlate,.,Filth_RubbleRock,Slate,Slate,Slate,Slate,Slate,Slate,ChunkSlate,.</li>
				<li>.,.,.,.,Slate,Slate,Filth_RubbleRock,Filth_RubbleRock,Wall_BlocksSlate,TorchWallLamp_West,.,.,Brazier_Steel,.,.,Slate,Slate,Filth_RubbleRock,ChunkSlate,Filth_RubbleRock,Filth_RubbleRock,Filth_RubbleRock,Filth_RubbleRock,Slate,Slate,.,.</li>
				<li>Slate,Slate,Slate,Slate,Slate,Slate,ChunkSlate,.,Door_BlocksSlate,.,.,.,.,.,.,Slate,Slate,.,.,ChunkSlate,.,.,Filth_RubbleRock,Slate,Slate,.,.</li>
				<li>Slate,Slate,Slate,Slate,Slate,Slate,.,.,Wall_BlocksSlate,Bed_WoodLog_Kemetic_East,.,.,.,.,Bed_WoodLog_Kemetic_West,Slate,Slate,.,.,Filth_RubbleRock,.,.,.,Slate,Slate,Slate,ChunkSlate</li>
				<li>Slate,Slate,Slate,Slate,Slate,Slate,.,.,Wall_BlocksSlate,EndTable_WoodLog_Kemetic_East,.,.,.,.,EndTable_WoodLog_Kemetic_West,Slate,Slate,ChunkSlate,DeathrestCasket_South,.,DeathrestCasket_South,.,DeathrestCasket_South,Slate,Slate,Slate,.</li>
				<li>.,.,.,.,Slate,Slate,Slate,Slate,Slate,Bed_WoodLog_Kemetic_East,.,.,.,.,Bed_WoodLog_Kemetic_West,Slate,Slate,ChunkSlate,Filth_RubbleRock,Filth_RubbleRock,Filth_RubbleRock,ChunkSlate,ChunkSlate,Slate,Slate,Slate,.</li>
				<li>.,.,.,ChunkSlate,Slate,Slate,Slate,Slate,Slate,Slate,Slate,Slate,Slate,Slate,Slate,Slate,Slate,Slate,Slate,Slate,Slate,Slate,Slate,Slate,Slate,.,.</li>
				<li>.,.,.,.,Slate,Slate,.,.,.,Slate,Slate,Slate,Slate,Slate,Slate,Slate,Slate,Slate,Slate,Slate,Slate,.,Slate,Slate,.,.,.</li>
				<li>.,.,.,.,.,.,.,.,.,.,Slate,Slate,Slate,Slate,.,.,Slate,Slate,Slate,Slate,Slate,.,Slate,Slate,.,.,.</li>
				<li>.,.,.,.,.,.,ChunkSlate,.,.,.,Slate,Slate,Slate,Slate,.,ChunkSlate,.,.,Slate,Slate,Slate,.,.,.,ChunkSlate,.,.</li>
				<li>.,.,.,.,.,.,.,.,.,.,.,.,.,.,.,.,.,.,Slate,Slate,Slate,.,.,.,.,.,.</li>
				<li>.,.,.,.,.,.,.,.,.,.,.,.,ChunkSlate,.,.,.,.,.,.,.,.,.,ChunkSlate,.,.,.,.</li>
			</li>
			<li>
				<li>.,.,.,.,.,.,.,.,.,.,.,.,.,.,.,.,.,.,.,.,.,.,.,.,.,.,.</li>
				<li>.,.,.,.,.,.,.,.,.,.,.,.,.,.,.,.,.,.,.,.,.,.,.,.,.,.,.</li>
				<li>.,.,.,.,.,.,.,.,.,.,.,.,.,.,.,.,.,.,.,.,.,.,.,.,.,.,.</li>
				<li>.,.,.,.,.,.,.,.,.,.,.,.,.,.,.,.,.,.,.,.,.,.,.,.,.,.,.</li>
				<li>.,.,.,.,.,.,.,.,.,.,.,.,.,.,.,.,.,.,.,.,.,.,.,.,.,.,.</li>
				<li>.,.,.,.,.,.,.,.,.,.,.,.,.,.,.,.,.,.,.,.,.,.,.,.,.,.,.</li>
				<li>.,.,.,.,.,.,.,.,.,.,.,.,.,.,.,.,.,.,.,.,.,.,.,.,.,.,.</li>
				<li>.,.,.,.,.,.,.,.,.,.,.,.,.,.,.,.,.,.,.,.,.,.,.,.,.,.,.</li>
				<li>.,.,.,.,.,.,.,.,.,.,.,.,.,.,.,.,.,.,.,.,.,.,.,.,.,.,.</li>
				<li>.,.,.,.,.,.,.,.,.,.,.,.,.,.,.,.,.,.,.,.,.,.,.,.,.,.,.</li>
				<li>.,.,.,.,.,.,.,.,.,.,.,.,.,.,.,.,.,.,.,.,.,.,.,.,.,.,.</li>
				<li>.,.,.,.,.,.,.,.,.,.,.,.,.,.,.,.,.,.,.,.,.,.,.,.,.,.,.</li>
				<li>.,.,.,.,.,.,.,.,.,.,.,.,.,.,.,.,.,.,.,.,.,.,.,.,.,.,.</li>
				<li>.,.,.,.,.,.,.,.,.,.,.,.,.,.,.,.,.,.,.,.,.,.,.,.,.,.,.</li>
				<li>.,.,.,.,.,.,.,.,.,.,.,.,.,.,.,.,.,.,.,.,.,.,.,.,.,.,.</li>
				<li>.,.,.,.,.,.,.,.,.,.,.,.,.,.,.,.,.,.,.,.,.,.,.,.,.,.,.</li>
				<li>.,.,.,.,.,.,.,.,.,.,.,.,.,.,.,.,.,.,.,TorchWallLamp_North,.,.,.,.,.,.,.</li>
				<li>.,.,.,.,.,.,.,.,.,.,.,.,.,.,.,.,.,.,.,.,.,.,.,.,.,.,.</li>
				<li>.,.,.,.,.,.,.,.,.,.,.,.,.,.,.,.,.,.,.,.,.,.,.,.,.,.,.</li>
				<li>.,.,.,.,.,.,.,.,.,.,.,.,.,.,.,.,.,.,.,.,.,.,.,.,.,.,.</li>
				<li>.,.,.,.,.,.,.,.,.,.,.,.,.,.,.,.,.,.,.,.,.,.,.,.,.,.,.</li>
				<li>.,.,.,.,.,.,.,.,.,.,.,.,.,.,.,.,.,.,.,.,.,.,.,.,.,.,.</li>
				<li>.,.,.,.,.,.,.,.,.,.,.,.,.,.,.,.,.,.,.,.,.,.,.,.,.,.,.</li>
			</li>
		</layouts>
		<roofGrid>
			<li>.,.,.,.,.,.,.,.,.,.,.,.,.,.,.,.,.,.,.,.,.,.,.,.,.,.,.</li>
			<li>.,.,.,.,.,.,.,.,.,.,.,.,.,.,.,.,.,.,.,.,.,.,.,.,.,.,.</li>
			<li>.,.,.,.,.,.,.,.,.,.,.,.,.,.,.,.,.,.,.,.,.,.,.,.,.,.,.</li>
			<li>.,.,.,.,.,.,.,.,.,.,.,.,.,.,.,.,.,.,.,.,.,.,.,.,.,.,.</li>
			<li>.,.,.,.,.,.,.,.,.,.,.,.,.,.,.,.,.,.,.,.,.,.,.,.,.,.,.</li>
			<li>.,.,.,.,.,.,.,3,3,3,3,3,3,3,3,3,3,3,.,.,.,.,.,.,.,.,.</li>
			<li>.,.,.,.,.,.,.,3,3,3,3,3,3,3,3,3,3,3,.,.,.,.,.,.,.,.,.</li>
			<li>.,.,.,.,.,.,.,3,3,3,3,3,3,3,3,3,3,3,.,.,.,.,.,.,.,.,.</li>
			<li>.,.,.,.,.,.,.,3,3,3,3,3,3,3,3,3,3,3,.,.,.,.,.,.,.,.,.</li>
			<li>.,.,.,.,.,.,.,3,3,3,3,3,3,3,3,3,3,3,.,.,.,.,.,.,.,.,.</li>
			<li>.,.,.,.,.,.,.,3,3,3,3,3,3,3,3,3,3,3,.,.,.,.,.,.,.,.,.</li>
			<li>.,.,.,.,.,3,3,3,3,3,3,3,3,3,3,3,3,3,3,3,3,3,3,3,.,.,.</li>
			<li>.,.,.,.,.,3,3,3,3,3,3,3,3,3,3,3,3,3,3,3,3,3,3,3,.,.,.</li>
			<li>.,.,.,.,.,3,3,3,3,3,3,3,3,3,3,3,3,3,3,3,3,3,3,3,.,.,.</li>
			<li>.,.,.,.,.,3,3,3,3,3,3,3,3,3,3,3,3,3,3,3,3,3,3,3,.,.,.</li>
			<li>.,.,.,.,.,3,3,3,3,3,3,3,3,3,3,3,3,3,3,3,3,3,3,3,.,.,.</li>
			<li>.,.,.,.,.,3,3,3,3,3,3,3,3,3,3,3,3,3,3,3,3,3,3,3,.,.,.</li>
			<li>.,.,.,.,.,3,3,3,3,3,3,3,3,3,3,3,3,3,3,3,3,3,3,3,.,.,.</li>
			<li>.,.,.,.,.,.,.,.,.,.,.,.,.,.,.,.,.,.,.,.,.,.,.,.,.,.,.</li>
			<li>.,.,.,.,.,.,.,.,.,.,.,.,.,.,.,.,.,.,.,.,.,.,.,.,.,.,.</li>
			<li>.,.,.,.,.,.,.,.,.,.,.,.,.,.,.,.,.,.,.,.,.,.,.,.,.,.,.</li>
			<li>.,.,.,.,.,.,.,.,.,.,.,.,.,.,.,.,.,.,.,.,.,.,.,.,.,.,.</li>
			<li>.,.,.,.,.,.,.,.,.,.,.,.,.,.,.,.,.,.,.,.,.,.,.,.,.,.,.</li>
		</roofGrid>
		<terrainGrid>
			<li>.,.,.,.,.,.,.,.,.,.,.,.,.,.,.,.,.,.,.,.,.,.,.,.,.,.,.</li>
			<li>.,.,.,.,.,.,.,.,.,.,.,.,.,.,.,.,.,.,.,.,.,.,.,.,.,.,.</li>
			<li>.,.,.,.,.,.,.,.,.,.,.,.,.,.,.,.,.,.,.,.,.,.,.,.,.,.,.</li>
			<li>.,.,.,.,.,.,.,.,.,.,.,.,.,.,.,.,.,.,.,.,.,.,.,.,.,.,.</li>
			<li>.,.,.,.,.,.,.,Slate_RoughHewn,Slate_RoughHewn,Slate_RoughHewn,.,.,.,Slate_RoughHewn,Slate_RoughHewn,.,.,.,.,.,.,.,.,.,.,.,.</li>
			<li>.,.,.,.,.,.,.,Slate_RoughHewn,Slate_RoughHewn,Slate_RoughHewn,.,.,Slate_RoughHewn,Slate_RoughHewn,.,.,.,.,.,.,.,.,.,.,.,.,.</li>
			<li>.,.,.,.,.,.,.,Slate_RoughHewn,.,.,.,.,Slate_RoughHewn,Slate_RoughHewn,.,.,.,.,.,.,.,.,.,.,.,.,.</li>
			<li>.,.,.,.,.,.,.,Slate_RoughHewn,.,TileSlate,TileSlate,TileSlate,TileSlate,TileSlate,TileSlate,Slate_RoughHewn,Slate_RoughHewn,Slate_RoughHewn,Slate_RoughHewn,Slate_RoughHewn,.,.,.,.,.,.,.</li>
			<li>.,.,.,.,.,.,.,.,Slate_RoughHewn,TileSlate,TileSlate,TileSlate,TileSlate,TileSlate,TileSlate,Slate_RoughHewn,Slate_RoughHewn,Slate_RoughHewn,Slate_RoughHewn,.,.,.,.,.,.,.,.</li>
			<li>.,.,.,.,.,.,.,.,Slate_RoughHewn,TileSlate,TileSlate,TileSlate,TileSlate,TileSlate,TileSlate,Slate_RoughHewn,Slate_RoughHewn,Slate_RoughHewn,Slate_RoughHewn,Slate_RoughHewn,.,.,.,.,.,.,.</li>
			<li>.,.,.,.,Slate_RoughHewn,.,Slate_RoughHewn,Slate_RoughHewn,Slate_RoughHewn,TileSlate,TileSlate,TileSlate,TileSlate,TileSlate,TileSlate,Slate_RoughHewn,Slate_RoughHewn,Slate_RoughHewn,Slate_RoughHewn,.,.,.,.,.,.,.,.</li>
			<li>.,.,.,.,Slate_RoughHewn,.,Slate_RoughHewn,Slate_RoughHewn,Slate_RoughHewn,TileSlate,TileSlate,TileSlate,TileSlate,TileSlate,TileSlate,Slate_RoughHewn,Slate_RoughHewn,Slate_RoughHewn,Slate_RoughHewn,Slate_RoughHewn,Slate_RoughHewn,Slate_RoughHewn,Slate_RoughHewn,.,.,.,.</li>
			<li>.,.,.,.,.,.,Slate_RoughHewn,Slate_RoughHewn,Slate_RoughHewn,TileSlate,TileSlate,TileSlate,TileSlate,TileSlate,TileSlate,.,.,Slate_RoughHewn,Slate_RoughHewn,Slate_RoughHewn,Slate_RoughHewn,Slate_RoughHewn,Slate_RoughHewn,.,.,.,.</li>
			<li>.,.,.,.,.,.,Slate_RoughHewn,Slate_RoughHewn,Slate_RoughHewn,TileSlate,TileSlate,TileSlate,TileSlate,TileSlate,TileSlate,Slate_RoughHewn,Slate_RoughHewn,Slate_RoughHewn,Slate_RoughHewn,Slate_RoughHewn,Slate_RoughHewn,Slate_RoughHewn,Slate_RoughHewn,.,.,.,.</li>
			<li>.,.,.,.,.,.,Slate_RoughHewn,Slate_RoughHewn,Slate_RoughHewn,TileSlate,TileSlate,TileSlate,TileSlate,TileSlate,TileSlate,.,Slate_RoughHewn,Slate_RoughHewn,Slate_RoughHewn,Slate_RoughHewn,Slate_RoughHewn,Slate_RoughHewn,Slate_RoughHewn,Slate_RoughHewn,Slate_RoughHewn,.,.</li>
			<li>.,.,.,.,.,.,Slate_RoughHewn,Slate_RoughHewn,Slate_RoughHewn,TileSlate,TileSlate,TileSlate,TileSlate,TileSlate,TileSlate,.,Slate_RoughHewn,Slate_RoughHewn,Slate_RoughHewn,Slate_RoughHewn,Slate_RoughHewn,Slate_RoughHewn,Slate_RoughHewn,Slate_RoughHewn,Slate_RoughHewn,.,.</li>
			<li>.,.,.,.,.,.,.,.,Slate_RoughHewn,TileSlate,TileSlate,TileSlate,TileSlate,TileSlate,TileSlate,.,Slate_RoughHewn,Slate_RoughHewn,Slate_RoughHewn,Slate_RoughHewn,Slate_RoughHewn,Slate_RoughHewn,Slate_RoughHewn,Slate_RoughHewn,Slate_RoughHewn,.,.</li>
			<li>.,.,.,.,.,.,.,.,.,Slate_RoughHewn,.,.,.,.,.,.,Slate_RoughHewn,.,.,Slate_RoughHewn,Slate_RoughHewn,.,Slate_RoughHewn,Slate_RoughHewn,.,.,.</li>
			<li>.,.,.,.,.,.,.,.,.,.,Slate_RoughHewn,Slate_RoughHewn,Slate_RoughHewn,Slate_RoughHewn,.,.,Slate_RoughHewn,.,.,.,.,.,.,.,.,.,.</li>
			<li>.,.,.,.,.,.,.,.,.,.,.,.,.,.,.,.,.,.,Slate_RoughHewn,Slate_RoughHewn,Slate_RoughHewn,.,.,.,.,.,.</li>
			<li>.,.,.,.,.,.,.,.,.,.,.,.,.,.,.,.,.,.,.,.,.,.,.,.,.,.,.</li>
			<li>.,.,.,.,.,.,.,.,.,.,.,.,.,.,.,.,.,.,.,.,.,.,.,.,.,.,.</li>
			<li>.,.,.,.,.,.,.,.,.,.,.,.,.,.,.,.,.,.,.,.,.,.,.,.,.,.,.</li>
		</terrainGrid>
		<modRequirements>
			<li>ludeon.rimworld.biotech</li>
			<li>ludeon.rimworld.royalty</li>
		</modRequirements>
	</KCSG.StructureLayoutDef>
	<KCSG.StructureLayoutDef>
		<defName>AM_SanguophageCamp_Beta</defName>
		<spawnConduits>false</spawnConduits>
		<layouts>
			<li>
				<li>.,.,.,.,.,.,.,.,.,.,.,.,.,.,.,.,.,.,.,.,.,.,Granite,.,.,Granite,.,.,.</li>
				<li>.,.,.,.,.,.,.,.,.,.,.,.,.,.,.,.,.,.,.,.,.,.,Granite,Granite,Granite,Granite,Granite,Granite,.</li>
				<li>.,.,.,.,.,.,.,.,.,.,.,.,Column_BlocksSlate_Morbid,.,Column_BlocksSlate_Morbid,.,.,.,.,.,.,.,Granite,Granite,Granite,Granite,Granite,Granite,.</li>
				<li>.,.,.,.,.,.,.,.,.,.,Granite,Granite,Granite,.,Granite,Granite,Granite,Granite,.,Granite,Granite,Granite,Granite,Granite,Granite,Granite,.,.,.</li>
				<li>.,.,.,.,.,.,.,.,.,.,Granite,Granite,Granite,.,Granite,Granite,Granite,Granite,.,Granite,Granite,Granite,Granite,Granite,Granite,Granite,.,.,.</li>
				<li>.,.,.,.,.,.,Granite,Granite,Granite,Granite,Granite,Granite,Granite,Door_BlocksGranite,Granite,Granite,Granite,Granite,Granite,Granite,Granite,.,.,Bed_BlocksGranite_West,Granite,Granite,Granite,.,.</li>
				<li>.,.,.,.,.,.,.,Granite,Granite,Brazier_Steel,.,.,.,.,.,.,.,.,.,.,Wall_BlocksGranite,TorchWallLamp_Morbid_West,.,EndTable_BlocksSlate_East,Granite,Granite,.,.,.</li>
				<li>.,.,.,.,.,.,.,Granite,Granite,.,.,Column_BlocksSlate_Morbid,.,.,.,.,.,Column_BlocksSlate_Morbid,.,.,Door_BlocksGranite,.,.,Bed_BlocksGranite_West,Granite,Granite,Granite,.,.</li>
				<li>.,.,Granite,Granite,Granite,.,.,Granite,Granite,.,.,.,DiningChair_WoodLog_East,.,.,.,DiningChair_WoodLog_West,.,.,.,Wall_BlocksGranite,.,.,EndTable_BlocksSlate_East,Granite,Granite,.,.,.</li>
				<li>.,.,.,.,.,Granite,Granite,Granite,Granite,.,.,.,DiningChair_WoodLog_East,.,Table3x3c_BlocksSlate_Morbid,.,DiningChair_WoodLog_West,.,.,TorchWallLamp_Morbid_East,Wall_BlocksGranite,.,.,Bed_BlocksGranite_West,Granite,Granite,.,.,.</li>
				<li>.,Granite,Granite,Granite,Granite,Granite,Granite,Granite,Granite,.,.,Column_BlocksSlate_Morbid,DiningChair_WoodLog_East,.,.,.,DiningChair_WoodLog_West,Column_BlocksSlate_Morbid,.,.,Granite,Granite,Granite,Granite,Granite,.,.,.,.</li>
				<li>.,Granite,Granite,Granite,Granite,Granite,Granite,Granite,Granite,.,.,.,.,.,.,.,.,.,.,.,Granite,Granite,.,.,.,.,.,.,.</li>
				<li>.,.,.,.,Granite,Granite,Granite,Granite,Granite,Brazier_Steel,.,WallLamp_Morbid_North,.,.,AM_RaidSpawner,.,.,.,WallLamp_Morbid_North,PlantPot_BlocksSlate,Granite,Granite,.,.,.,.,.,.,.</li>
				<li>.,.,.,.,Granite,Granite,Granite,Granite,Granite,Wall_BlocksGranite,Door_BlocksGranite,Wall_BlocksGranite,Wall_BlocksGranite,Wall_BlocksGranite,Wall_BlocksGranite,Wall_BlocksGranite,Door_BlocksGranite,Wall_BlocksGranite,Wall_BlocksGranite,Wall_BlocksGranite,Granite,Granite,.,Granite,.,.,.,.,.</li>
				<li>.,.,.,.,.,Granite,PlantPot_BlocksSlate,.,.,.,.,.,Wall_BlocksGranite,.,.,.,.,.,.,Granite,Granite,.,.,Granite,.,.,.,.,.</li>
				<li>.,.,.,Granite,Granite,Granite,.,.,.,.,.,.,Wall_BlocksGranite,VRE_HemogenPipe,VRE_HemogenPipe,.,.,.,.,Granite,Granite,Granite,Granite,Granite,.,.,.,.,.</li>
				<li>.,.,.,Granite,Granite,Granite,.,DeathrestCasket_South,.,.,DeathrestCasket_South,.,Wall_BlocksGranite,.,VRE_HemogenPipe,.,.,.,ChunkGranite,Granite,Granite,Granite,Granite,Granite,Granite,.,.,.,.</li>
				<li>.,.,.,.,.,Granite,ChunkGranite,.,.,.,.,TorchWallLamp_Morbid_East,Wall_BlocksGranite,TorchWallLamp_Morbid_West,VRE_HemogenPipe,.,.,VRE_HemogenVat,.,Granite,Granite,Granite,Granite,Granite,Granite,.,.,.,.</li>
				<li>.,.,.,.,.,Granite,.,.,.,.,.,.,Wall_BlocksGranite,.,VRE_HemogenPipe,.,VRE_HemogenPipe,.,.,Granite,Granite,Granite,Granite,Granite,Granite,.,.,.,.</li>
				<li>.,.,Granite,Granite,Granite,Granite,.,DeathrestCasket_South,ChunkGranite,.,.,.,Wall_BlocksGranite,.,VRE_HemogenPipe,VRE_HemogenPipe,VRE_HemogenPipe,.,.,Granite,Granite,Granite,Granite,Granite,.,.,.,.,.</li>
				<li>.,.,.,.,.,Granite,.,ChunkGranite,ChunkGranite,.,Dresser_BlocksSlate_South,PlantPot_BlocksSlate,Wall_BlocksGranite,.,.,.,VRE_HemogenPipe,.,.,Granite,Granite,Granite,Granite,Granite,.,.,.,.,.</li>
				<li>.,.,.,.,.,Granite,Granite,Granite,Granite,Granite,Granite,Granite,Granite,ChunkGranite,.,.,VRE_HemogenPipe,.,.,Granite,Granite,Granite,Granite,Granite,Granite,Granite,.,.,.</li>
				<li>.,.,.,.,.,Granite,Granite,Granite,.,Granite,Granite,Granite,Granite,.,ChunkGranite,.,VRE_HemogenPipe,.,.,Granite,Granite,Granite,Granite,Granite,.,.,.,.,.</li>
				<li>.,.,.,.,.,Granite,Granite,Granite,Granite,Granite,Granite,Granite,Granite,.,.,.,.,.,Battery_North,Granite,.,Granite,Granite,Granite,Granite,.,.,.,.</li>
				<li>.,.,.,.,.,.,.,.,.,Granite,Granite,Granite,Granite,.,.,VRE_Draincasket_South,.,VRE_Draincasket_South,.,Granite,.,Granite,Granite,Granite,Granite,.,.,.,.</li>
				<li>.,.,.,.,.,.,.,.,.,Granite,Granite,Granite,Granite,Granite,Granite,Granite,Granite,Granite,Granite,Granite,.,.,Granite,.,.,.,.,.,.</li>
				<li>.,.,.,.,.,.,.,.,.,.,.,.,.,Granite,Granite,.,.,.,.,.,.,.,Granite,.,.,.,.,.,.</li>
				<li>.,.,.,.,.,.,.,.,.,.,.,.,.,Granite,Granite,.,.,.,.,.,.,.,.,.,.,.,.,.,.</li>
			</li>
			<li>
				<li>.,.,.,.,.,.,.,.,.,.,.,.,.,.,.,.,.,.,.,.,.,.,.,.,.,.,.,.,.</li>
				<li>.,.,.,.,.,.,.,.,.,.,.,.,.,.,.,.,.,.,.,.,.,.,.,.,.,.,.,.,.</li>
				<li>.,.,.,.,.,.,.,.,.,.,.,.,.,.,.,.,.,.,.,.,.,.,.,.,.,.,.,.,.</li>
				<li>.,.,.,.,.,.,.,.,.,.,.,.,.,.,.,.,.,.,.,.,.,.,.,.,.,.,.,.,.</li>
				<li>.,.,.,.,.,.,.,.,.,.,.,.,.,.,.,.,.,.,.,.,.,.,.,.,.,.,.,.,.</li>
				<li>.,.,.,.,.,.,.,.,.,.,.,.,.,.,.,.,.,.,.,.,.,.,.,.,.,.,.,.,.</li>
				<li>.,.,.,.,.,.,.,.,.,.,.,.,.,.,.,.,.,.,.,.,.,.,.,.,.,.,.,.,.</li>
				<li>.,.,.,.,.,.,.,.,.,.,.,.,.,.,.,.,.,.,.,.,.,.,.,.,.,.,.,.,.</li>
				<li>.,.,.,.,.,.,.,.,.,.,.,.,.,.,.,.,.,.,.,.,.,.,.,.,.,.,.,.,.</li>
				<li>.,.,.,.,.,.,.,.,.,.,.,.,.,.,.,.,.,.,.,.,.,.,.,.,.,.,.,.,.</li>
				<li>.,.,.,.,.,.,.,.,.,.,.,.,.,.,.,.,.,.,.,.,.,.,.,.,.,.,.,.,.</li>
				<li>.,.,.,.,.,.,.,.,.,.,.,.,.,.,.,.,.,.,.,.,.,.,.,.,.,.,.,.,.</li>
				<li>.,.,.,.,.,.,.,.,.,.,.,.,.,.,.,.,.,.,.,.,.,.,.,.,.,.,.,.,.</li>
				<li>.,.,.,.,.,.,PowerConduit,PowerConduit,PowerConduit,PowerConduit,PowerConduit,PowerConduit,PowerConduit,PowerConduit,PowerConduit,PowerConduit,PowerConduit,PowerConduit,PowerConduit,PowerConduit,.,.,.,.,.,.,.,.,.</li>
				<li>.,.,.,.,.,.,.,.,.,.,.,.,.,.,.,.,.,.,.,PowerConduit,.,.,.,.,.,.,.,.,.</li>
				<li>.,.,.,.,.,.,.,.,.,.,.,.,.,.,.,.,.,.,.,PowerConduit,.,.,.,.,.,.,.,.,.</li>
				<li>.,.,.,.,.,.,.,.,.,.,.,.,.,HemogenPack,.,.,.,.,.,PowerConduit,.,.,.,.,.,.,.,.,.</li>
				<li>.,.,.,.,.,.,.,.,.,.,.,.,.,Shelf_WoodLog_East,.,.,.,.,.,PowerConduit,.,.,.,.,.,.,.,.,.</li>
				<li>.,.,.,.,.,.,.,.,.,.,.,.,.,.,.,.,.,.,.,PowerConduit,.,.,.,.,.,.,.,.,.</li>
				<li>.,.,.,.,.,.,.,.,.,.,.,.,.,.,.,.,.,.,.,PowerConduit,.,.,.,.,.,.,.,.,.</li>
				<li>.,.,.,.,.,.,.,.,.,.,.,.,.,HemogenPack,.,.,.,.,.,PowerConduit,.,.,.,.,.,.,.,.,.</li>
				<li>.,.,.,.,.,.,.,.,.,.,.,.,.,Shelf_WoodLog_East,.,.,.,.,.,PowerConduit,.,.,.,.,.,.,.,.,.</li>
				<li>.,.,.,.,.,.,.,.,.,.,.,.,.,.,.,.,.,.,.,PowerConduit,.,.,.,.,.,.,.,.,.</li>
				<li>.,.,.,.,.,.,.,.,.,.,.,.,.,.,.,.,.,.,.,PowerConduit,.,.,.,.,.,.,.,.,.</li>
				<li>.,.,.,.,.,.,.,.,.,.,.,.,.,.,.,.,.,.,.,.,.,.,.,.,.,.,.,.,.</li>
				<li>.,.,.,.,.,.,.,.,.,.,.,.,.,.,.,.,.,.,.,.,.,.,.,.,.,.,.,.,.</li>
				<li>.,.,.,.,.,.,.,.,.,.,.,.,.,.,.,.,.,.,.,.,.,.,.,.,.,.,.,.,.</li>
				<li>.,.,.,.,.,.,.,.,.,.,.,.,.,.,.,.,.,.,.,.,.,.,.,.,.,.,.,.,.</li>
			</li>
			<li>
				<li>.,.,.,.,.,.,.,.,.,.,.,.,.,.,.,.,.,.,.,.,.,.,.,.,.,.,.,.,.</li>
				<li>.,.,.,.,.,.,.,.,.,.,.,.,.,.,.,.,.,.,.,.,.,.,.,.,.,.,.,.,.</li>
				<li>.,.,.,.,.,.,.,.,.,.,.,.,.,.,.,.,.,.,.,.,.,.,.,.,.,.,.,.,.</li>
				<li>.,.,.,.,.,.,.,.,.,.,.,.,.,.,.,.,.,.,.,.,.,.,.,.,.,.,.,.,.</li>
				<li>.,.,.,.,.,.,.,.,.,.,.,.,.,.,.,.,.,.,.,.,.,.,.,.,.,.,.,.,.</li>
				<li>.,.,.,.,.,.,.,.,.,.,.,.,.,.,.,.,.,.,.,.,.,.,.,.,.,.,.,.,.</li>
				<li>.,.,.,.,.,.,.,.,.,.,.,.,.,.,.,.,.,.,.,.,.,.,.,.,.,.,.,.,.</li>
				<li>.,.,.,.,.,.,.,.,.,.,.,.,.,.,.,.,.,.,.,.,.,.,.,.,.,.,.,.,.</li>
				<li>.,.,.,.,.,.,.,.,.,.,.,.,.,.,.,.,.,.,.,.,.,.,.,.,.,.,.,.,.</li>
				<li>.,.,.,.,.,.,.,.,.,.,.,.,.,.,.,.,.,.,.,.,.,.,.,.,.,.,.,.,.</li>
				<li>.,.,.,.,.,.,.,.,.,.,.,.,.,.,.,.,.,.,.,.,.,.,.,.,.,.,.,.,.</li>
				<li>.,.,.,.,.,.,.,.,.,.,.,.,.,.,.,.,.,.,.,.,.,.,.,.,.,.,.,.,.</li>
				<li>.,.,.,.,.,.,.,.,.,.,.,.,.,.,.,.,.,.,.,.,.,.,.,.,.,.,.,.,.</li>
				<li>.,.,.,.,.,.,.,.,.,.,.,.,.,.,.,.,.,.,.,.,.,.,.,.,.,.,.,.,.</li>
				<li>.,.,.,.,.,.,.,.,.,.,.,.,.,.,.,.,.,.,.,.,.,.,.,.,.,.,.,.,.</li>
				<li>.,.,.,.,.,.,.,.,.,.,.,.,.,.,.,.,.,.,.,.,.,.,.,.,.,.,.,.,.</li>
				<li>.,.,.,.,.,.,.,.,.,.,.,.,.,.,.,.,.,.,.,.,.,.,.,.,.,.,.,.,.</li>
				<li>.,.,.,.,.,.,.,.,.,.,.,.,.,HemogenPack,.,.,.,.,.,.,.,.,.,.,.,.,.,.,.</li>
				<li>.,.,.,.,.,.,.,.,.,.,.,.,.,.,.,.,.,.,.,.,.,.,.,.,.,.,.,.,.</li>
				<li>.,.,.,.,.,.,.,.,.,.,.,.,.,.,.,.,.,.,.,.,.,.,.,.,.,.,.,.,.</li>
				<li>.,.,.,.,.,.,.,.,.,.,.,.,.,.,.,.,.,.,.,.,.,.,.,.,.,.,.,.,.</li>
				<li>.,.,.,.,.,.,.,.,.,.,.,.,.,.,.,.,.,.,.,.,.,.,.,.,.,.,.,.,.</li>
				<li>.,.,.,.,.,.,.,.,.,.,.,.,.,.,.,.,.,.,.,.,.,.,.,.,.,.,.,.,.</li>
				<li>.,.,.,.,.,.,.,.,.,.,.,.,.,.,.,.,.,.,.,.,.,.,.,.,.,.,.,.,.</li>
				<li>.,.,.,.,.,.,.,.,.,.,.,.,.,.,.,.,.,.,.,.,.,.,.,.,.,.,.,.,.</li>
				<li>.,.,.,.,.,.,.,.,.,.,.,.,.,.,.,.,.,.,.,.,.,.,.,.,.,.,.,.,.</li>
				<li>.,.,.,.,.,.,.,.,.,.,.,.,.,.,.,.,.,.,.,.,.,.,.,.,.,.,.,.,.</li>
				<li>.,.,.,.,.,.,.,.,.,.,.,.,.,.,.,.,.,.,.,.,.,.,.,.,.,.,.,.,.</li>
			</li>
		</layouts>
		<roofGrid>
			<li>.,.,.,.,.,.,.,.,.,.,.,.,.,.,.,.,.,.,.,.,.,.,.,.,.,.,.,.,.</li>
			<li>.,.,.,.,.,.,.,.,.,.,.,.,.,.,.,.,.,.,.,.,.,.,.,.,.,.,.,.,.</li>
			<li>.,.,.,.,.,.,.,.,.,.,.,.,.,.,.,.,.,.,.,.,.,.,.,.,.,.,.,.,.</li>
			<li>.,.,.,.,.,.,.,.,.,.,.,.,.,.,.,.,.,.,.,.,.,.,.,.,.,.,.,.,.</li>
			<li>.,.,.,.,.,.,.,.,.,.,.,.,.,.,.,.,.,.,.,.,3,3,3,3,.,.,.,.,.</li>
			<li>.,.,.,.,.,.,.,.,3,3,3,3,3,3,3,3,3,3,3,3,3,3,3,3,.,.,.,.,.</li>
			<li>.,.,.,.,.,.,.,.,3,3,3,3,3,3,3,3,3,3,3,3,3,3,3,3,.,.,.,.,.</li>
			<li>.,.,.,.,.,.,.,.,3,3,3,3,3,3,3,3,3,3,3,3,3,3,3,3,.,.,.,.,.</li>
			<li>.,.,.,.,.,.,.,.,3,3,3,3,3,3,3,3,3,3,3,3,3,3,3,3,.,.,.,.,.</li>
			<li>.,.,.,.,.,.,.,.,3,3,3,3,3,3,3,3,3,3,3,3,3,3,3,3,.,.,.,.,.</li>
			<li>.,.,.,.,.,.,.,.,3,3,3,3,3,3,3,3,3,3,3,3,3,.,.,.,.,.,.,.,.</li>
			<li>.,.,.,.,.,.,.,.,3,3,3,3,3,3,3,3,3,3,3,3,3,.,.,.,.,.,.,.,.</li>
			<li>.,.,.,.,.,.,.,.,3,3,3,3,3,3,3,3,3,3,3,3,3,.,.,.,.,.,.,.,.</li>
			<li>.,.,.,.,.,3,3,3,3,3,3,3,3,3,3,3,3,3,3,3,3,.,.,.,.,.,.,.,.</li>
			<li>.,.,.,.,.,3,3,3,3,3,3,3,3,3,3,3,3,3,3,3,.,.,.,.,.,.,.,.,.</li>
			<li>.,.,.,.,.,3,3,3,3,3,3,3,3,3,3,3,3,3,3,3,.,.,.,.,.,.,.,.,.</li>
			<li>.,.,.,.,.,3,3,3,3,3,3,3,3,3,3,3,3,3,3,3,.,.,.,.,.,.,.,.,.</li>
			<li>.,.,.,.,.,3,3,3,3,3,3,3,3,3,3,3,3,3,3,3,.,.,.,.,.,.,.,.,.</li>
			<li>.,.,.,.,.,3,3,3,3,3,3,3,3,3,3,3,3,3,3,3,.,.,.,.,.,.,.,.,.</li>
			<li>.,.,.,.,.,3,3,3,3,3,3,3,3,3,3,3,3,3,3,3,.,.,.,.,.,.,.,.,.</li>
			<li>.,.,.,.,.,3,3,3,3,3,3,3,3,3,3,3,3,3,3,3,.,.,.,.,.,.,.,.,.</li>
			<li>.,.,.,.,.,3,3,3,3,3,3,3,3,3,3,3,3,3,3,3,.,.,.,.,.,.,.,.,.</li>
			<li>.,.,.,.,.,.,.,.,.,.,.,.,3,3,3,3,3,3,3,3,.,.,.,.,.,.,.,.,.</li>
			<li>.,.,.,.,.,.,.,.,.,.,.,.,3,3,3,3,3,3,3,3,.,.,.,.,.,.,.,.,.</li>
			<li>.,.,.,.,.,.,.,.,.,.,.,.,3,3,3,3,3,3,3,3,.,.,.,.,.,.,.,.,.</li>
			<li>.,.,.,.,.,.,.,.,.,.,.,.,3,3,3,3,3,3,3,3,.,.,.,.,.,.,.,.,.</li>
			<li>.,.,.,.,.,.,.,.,.,.,.,.,.,.,.,.,.,.,.,.,.,.,.,.,.,.,.,.,.</li>
			<li>.,.,.,.,.,.,.,.,.,.,.,.,.,.,.,.,.,.,.,.,.,.,.,.,.,.,.,.,.</li>
		</roofGrid>
		<terrainGrid>
			<li>.,.,.,.,.,.,.,.,.,.,.,.,.,.,.,.,.,.,.,.,.,.,.,.,.,.,.,.,.</li>
			<li>.,.,.,.,.,.,.,.,.,.,.,.,.,.,.,.,.,.,.,.,.,.,Granite_RoughHewn,.,.,.,.,.,.</li>
			<li>.,.,.,.,.,.,.,.,.,.,.,.,.,.,.,.,.,.,.,.,.,.,.,.,.,.,.,.,.</li>
			<li>.,.,.,.,.,.,.,.,.,.,.,.,.,.,.,.,.,.,.,.,.,.,.,.,.,.,.,.,.</li>
			<li>.,.,.,.,.,.,.,.,.,.,.,.,.,.,.,.,.,.,.,.,.,.,.,.,.,.,.,.,.</li>
			<li>.,.,.,.,.,.,.,Granite_RoughHewn,.,.,.,.,.,Granite_RoughHewn,Granite_RoughHewn,Granite_RoughHewn,Granite_RoughHewn,Granite_RoughHewn,.,.,Granite_RoughHewn,Granite_RoughHewn,Granite_RoughHewn,Granite_RoughHewn,.,Granite_RoughHewn,.,.,.</li>
			<li>.,.,.,.,.,.,.,.,.,TileGranite,TileGranite,TileGranite,TileGranite,TileGranite,TileGranite,TileGranite,TileGranite,TileGranite,TileGranite,TileGranite,Granite_RoughHewn,Granite_RoughHewn,Granite_RoughHewn,Granite_RoughHewn,.,.,.,.,.</li>
			<li>.,.,.,.,.,.,.,.,.,TileGranite,TileGranite,TileGranite,CarpetScarlet,CarpetScarlet,CarpetScarlet,CarpetScarlet,CarpetScarlet,TileGranite,TileGranite,TileGranite,Granite_RoughHewn,Granite_RoughHewn,Granite_RoughHewn,Granite_RoughHewn,Granite_RoughHewn,Granite_RoughHewn,.,.,.</li>
			<li>.,.,.,.,.,.,.,.,.,TileGranite,TileGranite,TileGranite,CarpetScarlet,CarpetScarlet,CarpetScarlet,CarpetScarlet,CarpetScarlet,TileGranite,TileGranite,TileGranite,Granite_RoughHewn,Granite_RoughHewn,Granite_RoughHewn,Granite_RoughHewn,Granite_RoughHewn,.,.,.,.</li>
			<li>.,.,.,.,.,.,.,Granite_RoughHewn,Granite_RoughHewn,TileGranite,TileGranite,TileGranite,CarpetScarlet,CarpetScarlet,CarpetScarlet,CarpetScarlet,CarpetScarlet,TileGranite,TileGranite,TileGranite,Granite_RoughHewn,Granite_RoughHewn,Granite_RoughHewn,Granite_RoughHewn,Granite_RoughHewn,.,.,.,.</li>
			<li>.,.,.,.,.,.,.,Granite_RoughHewn,Granite_RoughHewn,TileGranite,TileGranite,TileGranite,CarpetScarlet,CarpetScarlet,CarpetScarlet,CarpetScarlet,CarpetScarlet,TileGranite,TileGranite,TileGranite,.,.,.,.,.,.,.,.,.</li>
			<li>.,.,.,.,.,.,.,.,.,TileGranite,TileGranite,TileGranite,CarpetScarlet,CarpetScarlet,CarpetScarlet,CarpetScarlet,CarpetScarlet,TileGranite,TileGranite,TileGranite,Granite_RoughHewn,.,.,.,.,.,.,.,.</li>
			<li>.,.,.,.,.,Granite_RoughHewn,.,.,.,TileGranite,TileGranite,TileGranite,TileGranite,TileGranite,TileGranite,TileGranite,TileGranite,TileGranite,TileGranite,TileGranite,Granite_RoughHewn,.,.,.,.,.,.,.,.</li>
			<li>.,.,.,.,.,Granite_RoughHewn,.,.,.,Granite_RoughHewn,Granite_RoughHewn,Granite_RoughHewn,Granite_RoughHewn,Granite_RoughHewn,Granite_RoughHewn,Granite_RoughHewn,Granite_RoughHewn,Granite_RoughHewn,Granite_RoughHewn,Granite_RoughHewn,Granite_RoughHewn,.,.,.,.,.,.,.,.</li>
			<li>.,.,.,.,.,.,TileGranite,TileGranite,TileGranite,TileGranite,TileGranite,TileGranite,Granite_RoughHewn,TileGranite,TileGranite,CarpetScarlet,CarpetScarlet,TileGranite,TileGranite,.,.,.,.,.,.,.,.,.,.</li>
			<li>.,.,.,.,.,Granite_RoughHewn,TileGranite,TileGranite,TileGranite,TileGranite,TileGranite,TileGranite,Granite_RoughHewn,TileGranite,TileGranite,CarpetScarlet,CarpetScarlet,TileGranite,TileGranite,.,Granite_RoughHewn,.,.,.,.,.,.,.,.</li>
			<li>.,.,.,.,.,Granite_RoughHewn,TileGranite,TileGranite,TileGranite,TileGranite,TileGranite,TileGranite,Granite_RoughHewn,TileGranite,TileGranite,CarpetScarlet,CarpetScarlet,TileGranite,TileGranite,.,Granite_RoughHewn,.,.,.,.,.,.,.,.</li>
			<li>.,.,.,.,.,.,TileGranite,TileGranite,TileGranite,TileGranite,TileGranite,TileGranite,Granite_RoughHewn,TileGranite,TileGranite,CarpetScarlet,CarpetScarlet,TileGranite,TileGranite,.,.,.,.,Granite_RoughHewn,.,.,.,.,.</li>
			<li>.,.,.,.,.,.,TileGranite,TileGranite,TileGranite,TileGranite,TileGranite,TileGranite,Granite_RoughHewn,TileGranite,TileGranite,CarpetScarlet,CarpetScarlet,TileGranite,TileGranite,.,.,.,.,Granite_RoughHewn,.,.,.,.,.</li>
			<li>.,.,.,.,.,Granite_RoughHewn,TileGranite,TileGranite,TileGranite,TileGranite,TileGranite,TileGranite,Granite_RoughHewn,TileGranite,TileGranite,CarpetScarlet,CarpetScarlet,TileGranite,TileGranite,.,.,.,.,.,.,.,.,.,.</li>
			<li>.,.,.,.,.,.,TileGranite,TileGranite,TileGranite,TileGranite,TileGranite,TileGranite,Granite_RoughHewn,TileGranite,TileGranite,CarpetScarlet,CarpetScarlet,TileGranite,TileGranite,.,.,.,.,.,.,.,.,.,.</li>
			<li>.,.,.,.,.,Granite_RoughHewn,Granite_RoughHewn,Granite_RoughHewn,.,.,.,.,Granite_RoughHewn,TileGranite,TileGranite,CarpetScarlet,CarpetScarlet,TileGranite,TileGranite,Granite_RoughHewn,Granite_RoughHewn,.,.,.,.,.,.,.,.</li>
			<li>.,.,.,.,.,.,.,.,.,.,.,.,.,TileGranite,TileGranite,CarpetScarlet,CarpetScarlet,TileGranite,TileGranite,.,.,.,.,.,.,.,.,.,.</li>
			<li>.,.,.,.,.,.,.,Granite_RoughHewn,.,Granite_RoughHewn,Granite_RoughHewn,Granite_RoughHewn,Granite_RoughHewn,TileGranite,TileGranite,TileGranite,TileGranite,TileGranite,TileGranite,Granite_RoughHewn,.,.,.,.,.,.,.,.,.</li>
			<li>.,.,.,.,.,.,.,.,.,.,.,Granite_RoughHewn,.,TileGranite,TileGranite,TileGranite,TileGranite,TileGranite,TileGranite,.,.,.,.,.,.,.,.,.,.</li>
			<li>.,.,.,.,.,.,.,.,.,.,.,Granite_RoughHewn,.,.,Granite_RoughHewn,Granite_RoughHewn,Granite_RoughHewn,Granite_RoughHewn,Granite_RoughHewn,.,.,.,.,.,.,.,.,.,.</li>
			<li>.,.,.,.,.,.,.,.,.,.,.,.,.,.,.,.,.,.,.,.,.,.,.,.,.,.,.,.,.</li>
			<li>.,.,.,.,.,.,.,.,.,.,.,.,.,.,.,.,.,.,.,.,.,.,.,.,.,.,.,.,.</li>
		</terrainGrid>
		<modRequirements>
			<li>ludeon.rimworld.royalty</li>
			<li>sarg.alphamemes</li>
			<li>vanillaracesexpanded.sanguophage</li>
			<li>ludeon.rimworld.biotech</li>
		</modRequirements>
	</KCSG.StructureLayoutDef>
	<KCSG.StructureLayoutDef>
		<defName>AM_SanguophageCamp_Gamma</defName>
		<spawnConduits>false</spawnConduits>
		<layouts>
			<li>
				<li>.,.,.,.,.,.,.,.,.,.,.,.,.,.,.,.,.,Slate,.,.,.,.,Slate,.,.,.,.</li>
				<li>.,.,.,.,.,.,.,.,.,.,.,Slate,Slate,Slate,.,.,.,.,.,.,.,.,.,.,.,.,.</li>
				<li>.,.,.,.,.,.,ChunkSlate,.,.,Slate,Slate,.,.,.,.,.,.,Slate,Slate,Slate,Slate,Slate,.,.,.,.,.</li>
				<li>.,.,.,.,.,Slate,Slate,ChunkSlate,.,Slate,Slate,Slate,Slate,Slate,Slate,Slate,Slate,Slate,Slate,.,Slate,Slate,.,.,.,.,.</li>
				<li>.,.,.,.,ChunkSlate,.,Slate,Slate,.,.,Slate,Slate,Slate,Slate,Slate,Slate,Slate,Slate,Slate,.,Slate,Slate,Slate,.,.,.,.</li>
				<li>.,.,Slate,Slate,.,Slate,Slate,Slate,Slate,Slate,Slate,Slate,Slate,Slate,Slate,Slate,Slate,Slate,Slate,.,ChunkSlate,Slate,Slate,.,.,.,.</li>
				<li>.,.,Slate,Slate,Slate,Slate,Slate,Slate,Slate,Slate,Slate,Slate,Slate,.,.,.,.,.,.,.,.,.,.,Slate,.,.,.</li>
				<li>.,.,.,Slate,Slate,Slate,Slate,Slate,.,.,Slate,Slate,Slate,.,ChunkSlate,.,.,.,.,.,.,.,.,.,.,.,.</li>
				<li>.,.,.,.,.,Slate,Filth_RubbleRock,Filth_RubbleRock,.,.,.,.,.,.,.,ChunkSlate,ChunkSlate,.,.,.,.,ChunkSlate,.,.,.,.,.</li>
				<li>.,ChunkSlate,.,ChunkSlate,.,Slate,.,Slate,.,Slate,Slate,Slate,Slate,Slate,.,.,.,Slate,Slate,.,.,.,.,.,.,.,.</li>
				<li>.,.,.,.,.,Slate,Filth_RubbleRock,Slate,.,Slate,Slate,Slate,Slate,Slate,.,.,Slate,Slate,Slate,.,.,Slate,Slate,.,.,.,.</li>
				<li>.,.,Slate,Slate,Slate,Slate,Filth_RubbleRock,Slate,Slate,Slate,Slate,Slate,Slate,Slate,.,Slate,Slate,Slate,Slate,Slate,.,.,.,.,.,.,.</li>
				<li>.,.,Slate,Slate,Slate,ChunkSlate,Filth_RubbleRock,ChunkSlate,Shelf_BlocksSlate_North,.,AnimalBed_Leather_Panthera,PlantPot_BlocksSlate,Slate,.,.,Slate,Slate,Slate,Slate,Slate,Slate,.,.,.,.,.,.</li>
				<li>.,Slate,Slate,.,Slate,.,.,.,Filth_RubbleRock,.,.,Filth_RubbleRock,Slate,Slate,Slate,Slate,Slate,Slate,Slate,Slate,Slate,.,.,.,.,.,.</li>
				<li>.,Slate,Slate,.,Slate,Dresser_BlocksSlate_East,.,.,.,.,.,EndTable_BlocksSlate_West,Wall_BlocksSlate,.,.,.,.,Filth_RubbleRock,Filth_RubbleRock,Slate,Slate,.,.,.,.,.,.</li>
				<li>.,Slate,Slate,.,Slate,Bed_BlocksGranite_East,.,.,.,.,.,Bed_BlocksGranite_West,Wall_BlocksSlate,.,Stool_BlocksSlate_West,.,.,Stool_BlocksSlate_West,Filth_RubbleRock,Slate,.,.,Slate,.,.,.,.</li>
				<li>.,.,.,.,Slate,EndTable_BlocksSlate_East,.,.,.,.,.,.,Door_BlocksSlate,.,Stool_BlocksSlate_West,Table2x4c_BlocksSlate_North,.,Stool_BlocksSlate_West,ChunkSlate,Slate,.,Slate,Slate,.,.,.,.</li>
				<li>ChunkSlate,.,.,.,Slate,Bed_BlocksGranite_East,.,.,AM_RaidSpawner,.,.,.,Wall_BlocksSlate,.,Stool_BlocksSlate_West,.,.,ChunkSlate,Filth_RubbleRock,Slate,Slate,Slate,Slate,.,Slate,Slate,.</li>
				<li>.,ChunkSlate,.,.,Slate,EndTable_BlocksSlate_East,.,.,.,.,.,EndTable_BlocksSlate_West,Wall_BlocksSlate,TorchWallLamp_Morbid_West,Stool_BlocksSlate_West,.,.,Filth_RubbleRock,ChunkSlate,Slate,Slate,Slate,Slate,.,.,.,.</li>
				<li>.,.,Slate,Slate,Slate,Bed_BlocksGranite_East,.,.,.,.,.,Bed_BlocksGranite_West,Wall_BlocksSlate,.,.,.,.,Filth_RubbleRock,Filth_RubbleRock,Slate,Slate,Slate,Slate,.,.,.,.</li>
				<li>.,.,Slate,Slate,Slate,ChunkSlate,.,.,.,.,.,.,Wall_BlocksSlate,Wall_BlocksSlate,Wall_BlocksSlate,Door_BlocksSlate,Wall_BlocksSlate,Wall_BlocksSlate,Slate,Slate,Slate,Slate,Slate,.,.,.,.</li>
				<li>.,.,Slate,Slate,Slate,Filth_RubbleRock,.,Shelf_BlocksSlate_South,ChunkSlate,Filth_RubbleRock,.,Dresser_BlocksSlate_South,Wall_BlocksSlate,Brazier_Steel,.,.,Brazier_Steel,Slate,Slate,.,Slate,Slate,Slate,.,Slate,.,.</li>
				<li>.,.,Slate,Slate,Slate,Slate,Slate,Slate,Slate,Slate,Wall_BlocksSlate,Wall_BlocksSlate,Wall_BlocksSlate,TorchWallLamp_Morbid_West,.,.,.,Slate,Slate,Slate,Slate,Slate,Slate,.,Slate,.,.</li>
				<li>.,.,.,Slate,Slate,Slate,.,Slate,Slate,Slate,VRE_HemogenPipe,.,.,.,.,.,ChunkSlate,Slate,Slate,Slate,Slate,Slate,.,.,ChunkSlate,.,.</li>
				<li>.,.,.,Slate,Slate,Slate,.,Slate,.,Slate,VRE_HemogenPipe,.,.,.,.,.,.,Slate,Slate,Slate,Slate,Slate,ChunkSlate,.,.,.,.</li>
				<li>.,.,.,.,.,.,.,Slate,.,Slate,VRE_HemogenPipe,DeathrestCasket_South,.,DeathrestCasket_South,.,DeathrestCasket_South,TorchWallLamp_Morbid_East,Slate,Slate,Slate,.,.,.,.,.,.,.</li>
				<li>.,.,.,.,.,Slate,Slate,Slate,.,Slate,VRE_HemogenPipe,.,.,.,.,.,.,Slate,Slate,.,Slate,Slate,Slate,Slate,Slate,Slate,Slate</li>
				<li>.,.,.,.,.,Slate,Slate,Slate,.,Slate,VRE_HemogenPipe,VRE_HemogenPipe,VRE_HemogenPipe,VRE_HemogenPipe,VRE_HemogenPipe,.,VRE_Draincasket_South,Slate,Slate,Slate,Slate,Slate,Slate,Slate,Slate,Slate,Slate</li>
				<li>.,.,.,.,.,.,.,.,.,Slate,Wall_BlocksSlate,Wall_BlocksSlate,Wall_BlocksSlate,Door_BlocksSlate,Wall_BlocksSlate,Wall_BlocksSlate,Wall_BlocksSlate,Slate,Slate,Slate,Slate,Slate,.,.,.,.,.</li>
				<li>.,.,.,.,.,.,.,.,.,Slate,Slate,Wall_BlocksSlate,.,.,.,Filth_RubbleRock,Slate,Slate,.,.,Slate,Slate,Slate,.,.,.,.</li>
				<li>.,.,.,.,.,.,.,.,ChunkSlate,ChunkSlate,.,Wall_BlocksSlate,.,Shelf_BlocksSlate_South,ChunkSlate,ChunkSlate,Slate,Slate,Slate,.,Slate,Slate,Slate,.,.,.,.</li>
				<li>.,.,.,.,.,.,.,.,.,.,ChunkSlate,Slate,Slate,Slate,Slate,Slate,Slate,Slate,.,.,.,.,.,.,.,.,.</li>
				<li>.,.,.,.,.,.,.,.,.,.,.,.,Slate,Slate,Slate,Slate,.,.,.,.,.,.,.,.,.,.,.</li>
				<li>.,.,.,.,.,.,.,.,.,.,.,.,.,.,.,.,.,.,.,.,.,.,.,.,.,.,.</li>
			</li>
			<li>
				<li>.,.,.,.,.,.,.,.,.,.,.,.,.,.,.,.,.,.,.,.,.,.,.,.,.,.,.</li>
				<li>.,.,.,.,.,.,.,.,.,.,.,.,.,.,.,.,.,.,.,.,.,.,.,.,.,.,.</li>
				<li>.,.,.,.,.,.,.,.,.,.,.,.,.,.,.,.,.,.,.,.,.,.,.,.,.,.,.</li>
				<li>.,.,.,.,.,.,.,.,.,.,.,.,.,.,.,.,.,.,.,.,.,.,.,.,.,.,.</li>
				<li>.,.,.,.,.,.,.,.,.,.,.,.,.,.,.,.,.,.,.,.,.,.,.,.,.,.,.</li>
				<li>.,.,.,.,.,.,.,.,.,.,.,.,.,.,.,.,.,.,.,.,.,.,.,.,.,.,.</li>
				<li>.,.,.,.,.,.,.,.,.,.,.,.,.,.,.,.,.,.,.,.,.,.,.,.,.,.,.</li>
				<li>.,.,.,.,.,.,.,.,.,.,.,.,.,.,.,.,.,.,.,.,.,.,.,.,.,.,.</li>
				<li>.,.,.,.,.,.,.,.,.,.,.,.,.,.,.,.,.,.,.,.,.,.,.,.,.,.,.</li>
				<li>.,.,.,.,.,.,.,.,.,.,.,.,.,.,.,.,.,.,.,.,.,.,.,.,.,.,.</li>
				<li>.,.,.,.,.,.,.,.,.,.,.,.,.,.,.,.,.,.,.,.,.,.,.,.,.,.,.</li>
				<li>.,.,.,.,.,.,Door_BlocksSlate,.,.,.,.,.,.,.,.,.,.,.,.,.,.,.,.,.,.,.,.</li>
				<li>.,.,.,.,.,.,.,.,.,.,.,.,.,.,.,.,.,.,.,.,.,.,.,.,.,.,.</li>
				<li>.,.,.,.,.,.,.,.,.,.,.,.,.,.,.,.,.,.,.,.,.,.,.,.,.,.,.</li>
				<li>.,.,.,.,.,.,.,.,.,.,.,.,.,.,.,.,.,.,.,.,.,.,.,.,.,.,.</li>
				<li>.,.,.,.,.,.,.,.,.,.,.,.,.,.,.,.,.,.,.,.,.,.,.,.,.,.,.</li>
				<li>.,.,.,.,.,.,.,.,.,.,.,.,.,.,.,.,.,.,.,.,.,.,.,.,.,.,.</li>
				<li>.,.,.,.,.,.,.,.,.,.,.,.,.,.,.,.,.,Stool_BlocksSlate_West,.,.,.,.,.,.,.,.,.</li>
				<li>.,.,.,.,.,TorchWallLamp_Morbid_West,.,.,.,.,.,TorchWallLamp_Morbid_East,.,.,.,.,.,Stool_BlocksSlate_West,.,.,.,.,.,.,.,.,.</li>
				<li>.,.,.,.,.,.,.,.,.,.,.,.,.,.,.,.,.,.,.,.,.,.,.,.,.,.,.</li>
				<li>.,.,.,.,.,.,.,.,.,.,.,.,.,.,.,.,.,.,.,.,.,.,.,.,.,.,.</li>
				<li>.,.,.,.,.,.,.,.,.,.,.,.,.,.,.,.,.,.,.,.,.,.,.,.,.,.,.</li>
				<li>.,.,.,.,.,.,.,.,.,.,.,.,.,.,.,.,.,.,.,.,.,.,.,.,.,.,.</li>
				<li>.,.,.,.,.,.,.,.,.,.,.,.,.,.,.,.,.,.,.,.,.,.,.,.,.,.,.</li>
				<li>.,.,.,.,.,.,.,.,.,.,.,.,.,.,.,.,.,.,.,.,.,.,.,.,.,.,.</li>
				<li>.,.,.,.,.,.,.,.,.,.,.,.,.,.,.,.,.,.,.,.,.,.,.,.,.,.,.</li>
				<li>.,.,.,.,.,.,.,.,.,.,.,.,.,.,.,.,.,.,.,.,.,.,.,.,.,.,.</li>
				<li>.,.,.,.,.,.,.,.,.,.,.,Throne_BlocksSlate_South,.,.,.,.,.,.,.,.,.,.,.,.,.,.,.</li>
				<li>.,.,.,.,.,.,.,.,.,.,.,.,.,.,.,.,.,.,.,.,.,.,.,.,.,.,.</li>
				<li>.,.,.,.,.,.,.,.,.,.,.,.,.,.,.,.,.,.,.,.,.,.,.,.,.,.,.</li>
				<li>.,.,.,.,.,.,.,.,.,.,.,.,MealSurvivalPack,.,.,.,.,.,.,.,.,.,.,.,.,.,.</li>
				<li>.,.,.,.,.,.,.,.,.,.,.,.,.,.,.,.,.,.,.,.,.,.,.,.,.,.,.</li>
				<li>.,.,.,.,.,.,.,.,.,.,.,.,.,.,.,.,.,.,.,.,.,.,.,.,.,.,.</li>
				<li>.,.,.,.,.,.,.,.,.,.,.,.,.,.,.,.,.,.,.,.,.,.,.,.,.,.,.</li>
			</li>
		</layouts>
		<roofGrid>
			<li>.,.,.,.,.,.,.,.,.,.,.,.,.,.,.,.,.,.,.,.,.,.,.,.,.,.,.</li>
			<li>.,.,.,.,.,.,.,.,.,.,.,.,.,.,.,.,.,.,.,.,.,.,.,.,.,.,.</li>
			<li>.,.,.,.,.,.,.,.,.,.,.,.,.,.,.,.,.,.,.,.,.,.,.,.,.,.,.</li>
			<li>.,.,.,.,.,.,.,.,.,.,.,.,.,.,.,.,.,.,.,.,.,.,.,.,.,.,.</li>
			<li>.,.,.,.,.,.,.,.,.,.,.,.,.,.,.,.,.,.,.,.,.,.,.,.,.,.,.</li>
			<li>.,.,.,.,.,.,.,.,.,.,.,.,.,.,.,.,.,.,.,.,.,.,.,.,.,.,.</li>
			<li>.,.,.,.,.,.,.,.,.,.,.,.,.,.,.,.,.,.,.,.,.,.,.,.,.,.,.</li>
			<li>.,.,.,.,.,.,.,.,.,.,.,.,.,.,.,.,.,.,.,.,.,.,.,.,.,.,.</li>
			<li>.,.,.,.,.,.,.,.,.,.,.,.,.,.,.,.,.,.,.,.,.,.,.,.,.,.,.</li>
			<li>.,.,.,.,.,.,.,.,.,.,.,.,.,.,.,.,.,.,.,.,.,.,.,.,.,.,.</li>
			<li>.,.,.,.,.,.,.,.,.,.,.,.,.,.,.,.,.,.,.,.,.,.,.,.,.,.,.</li>
			<li>.,.,.,.,.,.,.,.,.,.,.,.,.,.,.,.,.,.,.,.,.,.,.,.,.,.,.</li>
			<li>.,.,.,.,3,3,3,3,3,3,3,3,.,.,.,.,.,.,.,.,.,.,.,.,.,.,.</li>
			<li>.,.,.,.,3,3,3,3,3,3,3,3,.,.,.,.,.,.,.,.,.,.,.,.,.,.,.</li>
			<li>.,.,.,.,3,3,3,3,3,3,3,3,3,3,3,3,3,3,3,3,.,.,.,.,.,.,.</li>
			<li>.,.,.,.,3,3,3,3,3,3,3,3,3,3,3,3,3,3,3,3,.,.,.,.,.,.,.</li>
			<li>.,.,.,.,3,3,3,3,3,3,3,3,3,3,3,3,3,3,3,3,.,.,.,.,.,.,.</li>
			<li>.,.,.,.,3,3,3,3,3,3,3,3,3,3,3,3,3,3,3,3,.,.,.,.,.,.,.</li>
			<li>.,.,.,.,3,3,3,3,3,3,3,3,3,3,3,3,3,3,3,3,.,.,.,.,.,.,.</li>
			<li>.,.,.,.,3,3,3,3,3,3,3,3,3,3,3,3,3,3,3,3,.,.,.,.,.,.,.</li>
			<li>.,.,.,.,3,3,3,3,3,3,3,3,3,3,3,3,3,3,3,3,.,.,.,.,.,.,.</li>
			<li>.,.,.,.,3,3,3,3,3,3,3,3,3,3,3,3,3,.,.,.,.,.,.,.,.,.,.</li>
			<li>.,.,.,.,3,3,3,3,3,3,3,3,3,3,3,3,3,.,.,.,.,.,.,.,.,.,.</li>
			<li>.,.,.,.,.,.,.,.,.,3,3,3,3,3,3,3,3,.,.,.,.,.,.,.,.,.,.</li>
			<li>.,.,.,.,.,.,.,.,.,3,3,3,3,3,3,3,3,.,.,.,.,.,.,.,.,.,.</li>
			<li>.,.,.,.,.,.,.,.,.,3,3,3,3,3,3,3,3,.,.,.,.,.,.,.,.,.,.</li>
			<li>.,.,.,.,.,.,.,.,.,3,3,3,3,3,3,3,3,.,.,.,.,.,.,.,.,.,.</li>
			<li>.,.,.,.,.,.,.,.,.,3,3,3,3,3,3,3,3,.,.,.,.,.,.,.,.,.,.</li>
			<li>.,.,.,.,.,.,.,.,.,3,3,3,3,3,3,3,3,.,.,.,.,.,.,.,.,.,.</li>
			<li>.,.,.,.,.,.,.,.,.,.,.,3,3,3,3,3,3,.,.,.,.,.,.,.,.,.,.</li>
			<li>.,.,.,.,.,.,.,.,.,.,.,3,3,3,3,3,3,.,.,.,.,.,.,.,.,.,.</li>
			<li>.,.,.,.,.,.,.,.,.,.,.,.,.,.,.,.,.,.,.,.,.,.,.,.,.,.,.</li>
			<li>.,.,.,.,.,.,.,.,.,.,.,.,.,.,.,.,.,.,.,.,.,.,.,.,.,.,.</li>
			<li>.,.,.,.,.,.,.,.,.,.,.,.,.,.,.,.,.,.,.,.,.,.,.,.,.,.,.</li>
		</roofGrid>
		<terrainGrid>
			<li>.,.,.,.,.,.,.,.,.,.,.,.,.,.,.,.,.,.,.,.,.,.,.,.,.,.,.</li>
			<li>.,.,.,.,.,.,.,.,.,.,.,.,.,.,.,.,.,.,.,.,.,.,.,.,.,.,.</li>
			<li>.,.,.,.,.,.,.,.,.,.,.,.,.,.,.,.,.,.,.,.,Slate_RoughHewn,.,.,.,.,.,.</li>
			<li>.,.,.,.,.,.,.,.,.,.,Slate_RoughHewn,.,.,.,.,.,.,.,.,.,.,.,.,.,.,.,.</li>
			<li>.,.,.,.,.,.,.,.,.,.,.,.,.,.,.,.,.,.,.,.,.,Slate_RoughHewn,.,.,.,.,.</li>
			<li>.,.,.,.,.,.,Slate_RoughHewn,Slate_RoughHewn,.,.,Slate_RoughHewn,.,.,.,.,.,.,.,.,.,.,Slate_RoughHewn,Slate_RoughHewn,.,.,.,.</li>
			<li>.,.,.,Slate_RoughHewn,.,.,.,.,.,.,Slate_RoughHewn,.,.,.,.,.,.,.,.,.,.,.,.,.,.,.,.</li>
			<li>.,.,.,.,.,.,.,.,.,.,.,.,.,.,.,.,.,.,.,.,.,.,.,.,.,.,.</li>
			<li>.,.,.,.,.,.,Slate_RoughHewn,Slate_RoughHewn,.,.,.,.,.,.,.,.,.,.,.,.,.,.,.,.,.,.,.</li>
			<li>.,.,.,.,.,.,Slate_RoughHewn,.,.,.,.,.,.,.,.,.,.,.,.,.,.,.,.,.,.,.,.</li>
			<li>.,.,.,.,.,.,Slate_RoughHewn,.,.,.,.,.,.,.,.,.,.,Slate_RoughHewn,.,.,.,.,.,.,.,.,.</li>
			<li>.,.,.,.,Slate_RoughHewn,Slate_RoughHewn,Slate_RoughHewn,Slate_RoughHewn,Slate_RoughHewn,Slate_RoughHewn,Slate_RoughHewn,Slate_RoughHewn,Slate_RoughHewn,.,.,.,.,Slate_RoughHewn,.,.,.,.,.,.,.,.,.</li>
			<li>.,.,.,.,Slate_RoughHewn,TileMarble,TileMarble,TileMarble,TileMarble,TileMarble,TileMarble,TileMarble,Slate_RoughHewn,.,.,.,.,Slate_RoughHewn,.,.,.,.,.,.,.,.,.</li>
			<li>.,.,.,.,.,TileMarble,TileMarble,TileMarble,TileMarble,TileMarble,TileMarble,TileMarble,Slate_RoughHewn,.,.,Slate_RoughHewn,Slate_RoughHewn,Slate_RoughHewn,.,.,.,.,.,.,.,.,.</li>
			<li>.,.,.,.,.,TileMarble,TileMarble,TileMarble,CarpetScarlet,TileMarble,TileMarble,TileMarble,PavedTile,PavedTile,PavedTile,PavedTile,PavedTile,PavedTile,PavedTile,Slate_RoughHewn,.,.,.,.,.,.,.</li>
			<li>.,.,.,.,.,TileMarble,TileMarble,TileMarble,CarpetScarlet,TileMarble,TileMarble,TileMarble,PavedTile,PavedTile,PavedTile,PavedTile,PavedTile,PavedTile,PavedTile,Slate_RoughHewn,.,.,.,.,.,.,.</li>
			<li>.,.,.,.,.,TileMarble,TileMarble,TileMarble,CarpetScarlet,TileMarble,TileMarble,TileMarble,PavedTile,PavedTile,PavedTile,PavedTile,PavedTile,PavedTile,PavedTile,.,.,.,.,.,.,.,.</li>
			<li>.,.,.,.,.,TileMarble,TileMarble,TileMarble,CarpetScarlet,TileMarble,TileMarble,TileMarble,PavedTile,PavedTile,PavedTile,PavedTile,PavedTile,PavedTile,PavedTile,Slate_RoughHewn,.,Slate_RoughHewn,Slate_RoughHewn,.,.,.,.</li>
			<li>.,.,.,.,.,TileMarble,TileMarble,TileMarble,CarpetScarlet,TileMarble,TileMarble,TileMarble,PavedTile,PavedTile,PavedTile,PavedTile,PavedTile,PavedTile,PavedTile,Slate_RoughHewn,Slate_RoughHewn,.,.,.,.,.,.</li>
			<li>.,.,.,.,Slate_RoughHewn,TileMarble,TileMarble,TileMarble,CarpetScarlet,TileMarble,TileMarble,TileMarble,PavedTile,PavedTile,PavedTile,PavedTile,PavedTile,PavedTile,PavedTile,Slate_RoughHewn,Slate_RoughHewn,.,.,.,.,.,.</li>
			<li>.,.,.,.,.,TileMarble,TileMarble,TileMarble,TileMarble,TileMarble,TileMarble,TileMarble,Slate_RoughHewn,Slate_RoughHewn,Slate_RoughHewn,Tile_MorbidSlate,Slate_RoughHewn,Slate_RoughHewn,.,.,Slate_RoughHewn,Slate_RoughHewn,Slate_RoughHewn,.,.,.,.</li>
			<li>.,.,.,.,.,TileMarble,TileMarble,TileMarble,TileMarble,TileMarble,TileMarble,TileMarble,Slate_RoughHewn,Tile_MorbidSlate,Tile_MorbidSlate,Tile_MorbidSlate,Tile_MorbidSlate,Slate_RoughHewn,.,.,Slate_RoughHewn,Slate_RoughHewn,.,.,.,.,.</li>
			<li>.,.,.,Slate_RoughHewn,Slate_RoughHewn,Slate_RoughHewn,.,.,Slate_RoughHewn,Slate_RoughHewn,Slate_RoughHewn,Slate_RoughHewn,Slate_RoughHewn,Tile_MorbidSlate,Tile_MorbidSlate,Tile_MorbidSlate,Tile_MorbidSlate,Slate_RoughHewn,Slate_RoughHewn,Slate_RoughHewn,Slate_RoughHewn,Slate_RoughHewn,.,.,.,.,.</li>
			<li>.,.,.,.,.,.,.,.,Slate_RoughHewn,Slate_RoughHewn,Tile_MorbidSlate,Tile_MorbidSlate,Tile_MorbidSlate,Tile_MorbidSlate,Tile_MorbidSlate,Tile_MorbidSlate,Tile_MorbidSlate,Slate_RoughHewn,Slate_RoughHewn,Slate_RoughHewn,.,.,.,.,.,.,.</li>
			<li>.,.,.,.,.,.,.,.,.,.,Tile_MorbidSlate,Tile_MorbidSlate,Tile_MorbidSlate,Tile_MorbidSlate,Tile_MorbidSlate,Tile_MorbidSlate,Tile_MorbidSlate,Slate_RoughHewn,Slate_RoughHewn,.,.,.,.,.,.,.,.</li>
			<li>.,.,.,.,.,.,.,.,.,.,Tile_MorbidSlate,Tile_MorbidSlate,Tile_MorbidSlate,Tile_MorbidSlate,Tile_MorbidSlate,Tile_MorbidSlate,Tile_MorbidSlate,Slate_RoughHewn,.,.,.,.,.,.,.,.,.</li>
			<li>.,.,.,.,.,Slate_RoughHewn,Slate_RoughHewn,.,.,.,Tile_MorbidSlate,Tile_MorbidSlate,Tile_MorbidSlate,Tile_MorbidSlate,Tile_MorbidSlate,Tile_MorbidSlate,Tile_MorbidSlate,.,.,.,.,.,.,.,.,.,.</li>
			<li>.,.,.,.,.,.,.,.,.,.,Tile_MorbidSlate,Tile_MorbidSlate,Tile_MorbidSlate,Tile_MorbidSlate,Tile_MorbidSlate,Tile_MorbidSlate,Tile_MorbidSlate,.,Slate_RoughHewn,.,.,.,.,.,.,.,.</li>
			<li>.,.,.,.,.,.,.,.,.,.,Slate_RoughHewn,Slate_RoughHewn,Slate_RoughHewn,Slate_RoughHewn,Slate_RoughHewn,Slate_RoughHewn,Slate_RoughHewn,.,.,.,Slate_RoughHewn,.,.,.,.,.,.</li>
			<li>.,.,.,.,.,.,.,.,.,.,.,Slate_RoughHewn,Tile_MorbidSlate,Tile_MorbidSlate,Tile_MorbidSlate,Tile_MorbidSlate,.,.,.,.,.,.,.,.,.,.,.</li>
			<li>.,.,.,.,.,.,.,.,.,.,.,Slate_RoughHewn,Tile_MorbidSlate,Tile_MorbidSlate,Tile_MorbidSlate,Tile_MorbidSlate,Slate_RoughHewn,Slate_RoughHewn,.,.,.,.,.,.,.,.,.</li>
			<li>.,.,.,.,.,.,.,.,.,.,.,.,.,.,.,Slate_RoughHewn,.,.,.,.,.,.,.,.,.,.,.</li>
			<li>.,.,.,.,.,.,.,.,.,.,.,.,.,.,.,.,.,.,.,.,.,.,.,.,.,.,.</li>
			<li>.,.,.,.,.,.,.,.,.,.,.,.,.,.,.,.,.,.,.,.,.,.,.,.,.,.,.</li>
		</terrainGrid>
		<terrainColorGrid>
			<li>.,.,.,.,.,.,.,.,.,.,.,.,.,.,.,.,.,.,.,.,.,.,.,.,.,.,.</li>
			<li>.,.,.,.,.,.,.,.,.,.,.,.,.,.,.,.,.,.,.,.,.,.,.,.,.,.,.</li>
			<li>.,.,.,.,.,.,.,.,.,.,.,.,.,.,.,.,.,.,.,.,.,.,.,.,.,.,.</li>
			<li>.,.,.,.,.,.,.,.,.,.,.,.,.,.,.,.,.,.,.,.,.,.,.,.,.,.,.</li>
			<li>.,.,.,.,.,.,.,.,.,.,.,.,.,.,.,.,.,.,.,.,.,.,.,.,.,.,.</li>
			<li>.,.,.,.,.,.,.,.,.,.,.,.,.,.,.,.,.,.,.,.,.,.,.,.,.,.,.</li>
			<li>.,.,.,.,.,.,.,.,.,.,.,.,.,.,.,.,.,.,.,.,.,.,.,.,.,.,.</li>
			<li>.,.,.,.,.,.,.,.,.,.,.,.,.,.,.,.,.,.,.,.,.,.,.,.,.,.,.</li>
			<li>.,.,.,.,.,.,.,.,.,.,.,.,.,.,.,.,.,.,.,.,.,.,.,.,.,.,.</li>
			<li>.,.,.,.,.,.,.,.,.,.,.,.,.,.,.,.,.,.,.,.,.,.,.,.,.,.,.</li>
			<li>.,.,.,.,.,.,.,.,.,.,.,.,.,.,.,.,.,.,.,.,.,.,.,.,.,.,.</li>
			<li>.,.,.,.,.,.,.,.,.,.,.,.,.,.,.,.,.,.,.,.,.,.,.,.,.,.,.</li>
			<li>.,.,.,.,.,Structure_Black,Structure_Black,Structure_Black,Structure_Black,Structure_Black,Structure_Black,Structure_Black,.,.,.,.,.,.,.,.,.,.,.,.,.,.,.</li>
			<li>.,.,.,.,.,Structure_Black,Structure_Black,Structure_Black,Structure_Black,Structure_Black,Structure_Black,Structure_Black,.,.,.,.,.,.,.,.,.,.,.,.,.,.,.</li>
			<li>.,.,.,.,.,Structure_Black,Structure_Black,Structure_Black,.,Structure_Black,Structure_Black,Structure_Black,.,Structure_Black,Structure_Black,Structure_Black,Structure_Black,Structure_Black,Structure_Black,.,.,.,.,.,.,.,.</li>
			<li>.,.,.,.,.,Structure_Black,Structure_Black,Structure_Black,.,Structure_Black,Structure_Black,Structure_Black,.,Structure_Black,Structure_Black,Structure_Black,Structure_Black,Structure_Black,Structure_Black,.,.,.,.,.,.,.,.</li>
			<li>.,.,.,.,.,Structure_Black,Structure_Black,Structure_Black,.,Structure_Black,Structure_Black,Structure_Black,Structure_Black,Structure_Black,Structure_Black,Structure_Black,Structure_Black,Structure_Black,Structure_Black,.,.,.,.,.,.,.,.</li>
			<li>.,.,.,.,.,Structure_Black,Structure_Black,Structure_Black,.,Structure_Black,Structure_Black,Structure_Black,.,Structure_Black,Structure_Black,Structure_Black,Structure_Black,Structure_Black,Structure_Black,.,.,.,.,.,.,.,.</li>
			<li>.,.,.,.,.,Structure_Black,Structure_Black,Structure_Black,.,Structure_Black,Structure_Black,Structure_Black,.,Structure_Black,Structure_Black,Structure_Black,Structure_Black,Structure_Black,Structure_Black,.,.,.,.,.,.,.,.</li>
			<li>.,.,.,.,.,Structure_Black,Structure_Black,Structure_Black,.,Structure_Black,Structure_Black,Structure_Black,.,Structure_Black,Structure_Black,Structure_Black,Structure_Black,Structure_Black,Structure_Black,.,.,.,.,.,.,.,.</li>
			<li>.,.,.,.,.,Structure_Black,Structure_Black,Structure_Black,Structure_Black,Structure_Black,Structure_Black,Structure_Black,.,.,.,Structure_Black,.,.,.,.,.,.,.,.,.,.,.</li>
			<li>.,.,.,.,.,Structure_Black,Structure_Black,Structure_Black,Structure_Black,Structure_Black,Structure_Black,Structure_Black,.,.,.,.,.,.,.,.,.,.,.,.,.,.,.</li>
			<li>.,.,.,.,.,.,.,.,.,.,.,.,.,.,.,.,.,.,.,.,.,.,.,.,.,.,.</li>
			<li>.,.,.,.,.,.,.,.,.,.,.,.,.,.,.,.,.,.,.,.,.,.,.,.,.,.,.</li>
			<li>.,.,.,.,.,.,.,.,.,.,.,.,.,.,.,.,.,.,.,.,.,.,.,.,.,.,.</li>
			<li>.,.,.,.,.,.,.,.,.,.,.,.,.,.,.,.,.,.,.,.,.,.,.,.,.,.,.</li>
			<li>.,.,.,.,.,.,.,.,.,.,.,.,.,.,.,.,.,.,.,.,.,.,.,.,.,.,.</li>
			<li>.,.,.,.,.,.,.,.,.,.,.,.,.,.,.,.,.,.,.,.,.,.,.,.,.,.,.</li>
			<li>.,.,.,.,.,.,.,.,.,.,.,.,.,.,.,.,.,.,.,.,.,.,.,.,.,.,.</li>
			<li>.,.,.,.,.,.,.,.,.,.,.,.,.,.,.,.,.,.,.,.,.,.,.,.,.,.,.</li>
			<li>.,.,.,.,.,.,.,.,.,.,.,.,.,.,.,.,.,.,.,.,.,.,.,.,.,.,.</li>
			<li>.,.,.,.,.,.,.,.,.,.,.,.,.,.,.,.,.,.,.,.,.,.,.,.,.,.,.</li>
			<li>.,.,.,.,.,.,.,.,.,.,.,.,.,.,.,.,.,.,.,.,.,.,.,.,.,.,.</li>
			<li>.,.,.,.,.,.,.,.,.,.,.,.,.,.,.,.,.,.,.,.,.,.,.,.,.,.,.</li>
		</terrainColorGrid>
		<modRequirements>
			<li>sarg.alphamemes</li>
			<li>ludeon.rimworld.royalty</li>
			<li>vanillaracesexpanded.sanguophage</li>
			<li>ludeon.rimworld.biotech</li>
		</modRequirements>
	</KCSG.StructureLayoutDef>
	<KCSG.StructureLayoutDef>
		<defName>AM_SanguophageCamp_Delta</defName>
		<spawnConduits>false</spawnConduits>
		<layouts>
			<li>
				<li>.,.,.,.,.,.,.,.,.,.,.,.,.,.,.,.,.,.,.,.,.,.,.,.,.,.,.,.,Slate,Slate,.,.,Slate,Slate,Slate,Slate,.,.,.,.,.</li>
				<li>.,.,.,.,.,.,.,.,.,.,.,.,.,.,.,.,.,.,.,.,.,.,.,.,ChunkSlate,.,.,.,Slate,Slate,.,.,.,.,.,.,.,.,.,.,.</li>
				<li>.,.,.,.,.,.,.,ChunkSlate,.,.,.,Sandbags_Cloth,Sandbags_Cloth,Sandbags_Cloth,Sandbags_Cloth,Sandbags_Cloth,Sandbags_Cloth,.,ChunkSlate,.,.,ChunkSlate,.,.,.,Slate,Slate,Slate,Slate,Slate,Slate,Slate,Slate,Slate,Slate,Slate,.,.,.,.,.</li>
				<li>.,.,.,.,.,.,.,.,.,.,.,Sandbags_Cloth,Column_BlocksSlate_Morbid,.,.,.,Sandbags_Cloth,Column_BlocksSlate_Morbid,.,.,.,.,Column_BlocksSlate_Morbid,.,.,Slate,Slate,Slate,Slate,Slate,Slate,Slate,Slate,.,.,.,.,.,.,.,.</li>
				<li>.,.,.,.,.,ChunkSlate,.,.,.,Slate,Slate,Slate,Slate,Slate,.,Slate,Slate,Slate,Slate,Slate,Slate,Slate,Slate,Slate,Slate,Slate,Slate,Slate,Slate,Slate,Slate,Slate,Slate,ChunkSlate,.,Slate,Slate,Slate,Slate,.,.</li>
				<li>.,.,.,.,.,.,.,.,.,Slate,Slate,Slate,Slate,Slate,.,Slate,Slate,Slate,Slate,Slate,Slate,Slate,Slate,Slate,Slate,Slate,Slate,Slate,Slate,Slate,Slate,Slate,Slate,Slate,.,Slate,Slate,Slate,Slate,.,.</li>
				<li>.,.,.,.,.,.,.,.,.,Slate,Slate,Slate,Slate,Slate,.,.,.,.,Slate,Slate,Slate,Slate,Slate,Slate,Slate,Slate,Slate,Slate,Slate,Slate,Slate,Slate,Slate,Slate,ChunkSlate,Slate,Slate,Slate,Slate,.,.</li>
				<li>.,.,.,.,.,Slate,Slate,Slate,Slate,Slate,Slate,Slate,.,.,ChunkSlate,Skullspike_Steel,Slate,.,Slate,Slate,Wall_BlocksSlate,Wall_BlocksSlate,Wall_BlocksSlate,Slate,Slate,Slate,Wall_BlocksSlate,Slate,Slate,Slate,Slate,Slate,Slate,Slate,.,Slate,Slate,Slate,Slate,.,.</li>
				<li>.,.,.,.,Slate,Slate,Slate,Slate,Slate,Slate,Slate,Slate,.,ChunkSlate,.,.,Slate,.,Slate,Slate,Slate,Slate,Slate,Slate,Slate,Slate,Slate,Slate,Slate,Slate,Slate,Slate,Slate,Slate,Column_BlocksSlate_Morbid,.,.,.,.,.,.</li>
				<li>.,.,.,.,Slate,Slate,.,.,Slate,Slate,Slate,ChunkSlate,.,ChunkSlate,.,.,Slate,Sandbags_Cloth,Slate,Slate,Slate,Slate,Slate,Slate,Slate,Slate,Slate,Slate,Slate,Slate,Slate,Slate,Slate,Slate,.,.,.,.,.,.,.</li>
				<li>.,.,.,.,Slate,Slate,.,.,Slate,Slate,Slate,.,.,.,Slate,Slate,Slate,.,Filth_RubbleRock,Filth_RubbleRock,.,Slate,Slate,Slate,Slate,Slate,Slate,Slate,Slate,Slate,Slate,Slate,Slate,Slate,.,.,.,.,.,.,.</li>
				<li>.,.,.,ChunkSlate,.,ChunkSlate,ChunkSlate,.,Slate,Slate,Slate,Slate,.,.,Slate,Slate,.,Skullspike_Steel,Slate,Slate,Filth_RubbleRock,Slate,Slate,Slate,Slate,Slate,Slate,Slate,Slate,Slate,Slate,Slate,Slate,Slate,Slate,.,.,.,.,.,.</li>
				<li>.,.,.,.,Slate,Slate,.,.,Slate,Slate,Slate,Slate,Slate,Slate,Slate,Slate,Slate,Slate,Slate,Slate,Filth_RubbleRock,Slate,Slate,Slate,Slate,Slate,Slate,Slate,Slate,Slate,Slate,Slate,Slate,Slate,Slate,ChunkSlate,.,.,Slate,Slate,Slate</li>
				<li>.,.,.,.,Slate,Slate,.,.,Slate,Slate,Slate,Slate,Slate,Slate,Slate,Slate,Slate,Slate,Slate,Slate,Filth_RubbleRock,Slate,Slate,Slate,Slate,Slate,Slate,Slate,Slate,Wall_BlocksSlate,Wall_BlocksSlate,Wall_BlocksSlate,Wall_BlocksSlate,Wall_BlocksSlate,Slate,ChunkSlate,.,.,Slate,Slate,Slate</li>
				<li>.,.,.,Slate,Slate,.,.,.,Slate,Slate,Slate,Slate,Battery_North,.,VRE_HemogenVat,.,.,.,Battery_North,Slate,.,Slate,.,Bed_BlocksGranite_North,EndTable_BlocksSlate_North,Bed_BlocksGranite_North,EndTable_BlocksSlate_North,Bed_BlocksGranite_North,Slate,Wall_BlocksSlate,Wall_BlocksSlate,Wall_BlocksSlate,Wall_BlocksSlate,Wall_BlocksSlate,Slate,.,.,.,Slate,Slate,Slate</li>
				<li>.,.,.,Slate,Slate,.,.,.,.,Slate,Slate,Slate,.,VRE_HemogenPipe,.,.,.,.,.,Slate,Filth_RubbleRock,Slate,.,.,.,.,.,.,Slate,Slate,Slate,Slate,Slate,Slate,Slate,.,ChunkSlate,.,Slate,Slate,Slate</li>
				<li>.,.,Slate,Slate,Slate,Slate,Slate,Slate,Slate,Slate,Slate,Slate,TorchWallLamp_Morbid_West,.,.,.,.,.,TorchWallLamp_Morbid_East,Slate,Filth_RubbleRock,Slate,TorchWallLamp_Morbid_West,.,.,.,.,.,Slate,Slate,Slate,Slate,Slate,Slate,Slate,.,.,.,Slate,Slate,Slate</li>
				<li>.,.,Slate,Slate,Slate,Slate,Slate,Slate,Slate,Slate,Slate,Slate,VRE_HemogenPipe,.,Ideogram_Flesh_North,.,.,.,.,Slate,Filth_RubbleRock,Slate,.,.,.,.,.,Dresser_BlocksSlate_West,Slate,Slate,Slate,Slate,Slate,Slate,.,.,Slate,Slate,Slate,Slate,Slate</li>
				<li>.,.,Slate,Slate,Slate,Slate,Slate,Slate,Slate,Slate,Slate,Slate,VRE_HemogenPipe,.,.,.,AG_GrayStatue_North,.,.,Slate,Filth_RubbleRock,Slate,EndTable_BlocksSlate_South,Bed_BlocksGranite_South,EndTable_BlocksSlate_South,Bed_BlocksGranite_South,.,.,Slate,Slate,Slate,Slate,Slate,Slate,Column_BlocksSlate_Morbid,.,Slate,Slate,Slate,Slate,.</li>
				<li>.,.,.,.,.,.,.,Column_BlocksSlate_Morbid,.,.,Slate,Slate,Slate,Door_BlocksSlate,Slate,Slate,Slate,Slate,Slate,Slate,Filth_RubbleRock,Slate,Slate,Slate,Slate,Slate,Door_BlocksSlate,Slate,Slate,Slate,Slate,Slate,Slate,Slate,.,ChunkSlate,Slate,Slate,Slate,Slate,.</li>
				<li>ChunkSlate,.,ChunkSlate,.,ChunkSlate,.,.,Slate,Slate,Slate,Slate,ChunkSlate,Filth_RubbleRock,Filth_RubbleRock,Slate,Slate,Slate,Slate,ChunkSlate,Filth_RubbleRock,Filth_RubbleRock,.,TorchWallLamp_Morbid_East,Slate,Slate,Slate,.,.,PlantPot_BlocksSlate,.,.,Slate,Slate,Slate,.,.,Slate,Slate,Slate,Slate,.</li>
				<li>.,.,.,.,.,.,.,Slate,Slate,Slate,.,.,VRE_HemogenPipe,.,.,Slate,Slate,.,.,.,.,.,.,.,Slate,.,.,.,.,.,.,.,Slate,Slate,.,.,.,.,.,.,.</li>
				<li>.,.,Slate,Slate,Slate,Slate,Slate,.,.,Slate,.,.,.,.,.,Slate,Slate,.,Stool_BlocksSlate_West,.,.,.,Stool_BlocksSlate_Morbid_East,.,Slate,.,.,Shelf_BlocksSlate_South,.,.,Shelf_BlocksSlate_South,.,Slate,Slate,Slate,Slate,Slate,Slate,.,.,.</li>
				<li>.,.,Slate,Slate,Slate,Slate,Slate,.,.,Slate,.,.,VRE_Draincasket_South,.,.,.,Filth_RubbleRock,.,Stool_BlocksSlate_West,.,Table3x3c_BlocksSlate_Morbid,.,Stool_BlocksSlate_Morbid_East,.,Filth_RubbleRock,.,.,.,.,.,.,.,Slate,Slate,Slate,Slate,Slate,Slate,.,.,.</li>
				<li>.,.,.,.,Slate,Slate,Slate,Slate,Slate,Slate,.,.,VRE_HemogenPipe,.,.,Slate,Slate,.,Stool_BlocksSlate_West,.,.,.,Stool_BlocksSlate_Morbid_East,.,Slate,.,.,Bookcase_BlocksSlate_South,.,.,Bookcase_BlocksSlate_South,.,Slate,Slate,.,.,.,.,.,.,.</li>
				<li>ChunkSlate,.,.,.,Slate,Slate,Slate,Slate,Slate,Slate,.,.,.,.,TorchWallLamp_Morbid_East,Slate,Slate,TorchWallLamp_Morbid_West,.,.,Stool_BlocksSlate_Morbid_North,.,.,AG_GrayStatue_North,Slate,.,.,.,.,.,.,.,Slate,Slate,.,.,.,.,.,.,.</li>
				<li>.,.,.,.,Slate,Slate,Slate,Slate,Slate,Slate,Slate,.,VRE_Draincasket_South,AG_GrayStatue_North,Slate,Slate,Slate,Slate,Filth_RubbleRock,Filth_RubbleRock,Filth_RubbleRock,.,WallLamp_Morbid_North,Slate,Slate,Slate,.,Shelf_BlocksSlate_South,TorchWallLamp_Morbid_North,.,Shelf_BlocksSlate_South,Slate,Slate,Slate,Slate,Slate,Slate,Slate,Slate,Slate,Slate</li>
				<li>.,.,.,ChunkSlate,.,Slate,Slate,Slate,Slate,Slate,Slate,Slate,Slate,Slate,Slate,Slate,Slate,Slate,Slate,Slate,Filth_RubbleRock,Slate,Slate,Slate,Slate,Slate,Slate,Slate,Slate,Slate,Slate,Slate,Slate,Slate,Slate,Slate,Slate,Slate,Slate,Slate,Slate</li>
				<li>.,.,.,.,.,.,.,.,.,Slate,Slate,Slate,Slate,Slate,Slate,Slate,Slate,Slate,.,.,.,.,.,Slate,Slate,Slate,Slate,Slate,Slate,Slate,Slate,Slate,Slate,Slate,Slate,Slate,Slate,Slate,Slate,Slate,Slate</li>
				<li>.,.,.,.,ChunkSlate,.,Column_BlocksSlate_Morbid,.,Slate,Slate,Slate,Slate,Slate,Slate,Slate,Slate,Slate,.,.,.,.,.,.,.,Slate,Slate,Slate,Slate,Slate,Slate,Slate,Slate,Slate,Slate,.,.,.,Column_BlocksSlate_Morbid,.,.,.</li>
				<li>.,.,.,.,ChunkSlate,Slate,Slate,Slate,Slate,Wall_BlocksSlate,Slate,Slate,Slate,Slate,Slate,Slate,Slate,.,.,.,AM_RaidSpawner,.,.,.,Slate,Slate,Slate,Slate,Slate,Slate,Slate,Slate,Slate,Slate,.,.,.,.,.,.,.</li>
				<li>.,.,.,.,.,Slate,Slate,Slate,Slate,Wall_BlocksSlate,Slate,Slate,Slate,Slate,Slate,Slate,Slate,.,DarklightBrazier_Steel,.,.,.,DarklightBrazier_Steel,.,Slate,Slate,Slate,Slate,Slate,Slate,Slate,Slate,Slate,Slate,.,ChunkSlate,.,.,.,.,.</li>
				<li>.,.,.,.,.,Slate,Slate,Slate,Slate,Wall_BlocksSlate,Slate,Slate,Slate,Slate,Slate,Slate,Slate,.,.,.,.,.,.,.,Slate,Slate,Slate,Slate,Slate,Slate,Slate,Slate,Slate,Slate,.,.,ChunkSlate,.,.,.,.</li>
				<li>.,.,.,.,.,Slate,Slate,Slate,Slate,Wall_BlocksSlate,Slate,Slate,Slate,Slate,Slate,Slate,Slate,.,DarklightBrazier_Steel,.,.,.,DarklightBrazier_Steel,.,Slate,Slate,Slate,Slate,Slate,Slate,Slate,Slate,Slate,Slate,.,.,.,.,.,.,.</li>
				<li>.,.,.,Slate,Slate,Slate,Slate,Slate,Slate,Slate,Slate,Slate,Slate,Slate,Slate,Wall_BlocksSlate,Slate,.,.,.,DeathrestCasket_South,.,.,.,Slate,Slate,.,.,Slate,Slate,Slate,Slate,.,.,ChunkSlate,.,.,.,.,.,.</li>
				<li>.,.,.,Slate,Slate,Slate,Slate,Slate,Slate,Slate,Slate,Slate,Slate,Slate,Slate,Wall_BlocksSlate,Slate,.,DarklightBrazier_Steel,.,.,.,DarklightBrazier_Steel,.,Slate,Slate,.,ChunkSlate,Slate,Slate,Slate,Slate,.,.,.,.,.,.,.,.,.</li>
				<li>.,.,.,Slate,Slate,Slate,Slate,Slate,Slate,Slate,Slate,Slate,Slate,Slate,Slate,Wall_BlocksSlate,Wall_BlocksSlate,Slate,Slate,TorchWallLamp_Morbid_North,.,TorchWallLamp_Morbid_North,Wall_BlocksSlate,Slate,Slate,Slate,.,.,Slate,Slate,Slate,Slate,.,.,.,.,.,.,.,.,.</li>
				<li>.,.,.,Slate,Slate,Slate,Slate,Slate,Slate,Slate,Slate,Slate,Slate,Slate,Slate,Wall_BlocksSlate,Wall_BlocksSlate,Slate,Slate,Slate,Slate,Slate,Slate,Slate,Slate,Slate,.,ChunkSlate,Slate,Slate,Column_BlocksSlate_Morbid,.,.,.,.,.,.,.,.,.,.</li>
				<li>.,.,.,.,.,.,.,ChunkSlate,.,Slate,Slate,Slate,Slate,Slate,Wall_BlocksSlate,Wall_BlocksSlate,Wall_BlocksSlate,Wall_BlocksSlate,Slate,Wall_BlocksSlate,Wall_BlocksSlate,Wall_BlocksSlate,Wall_BlocksSlate,Wall_BlocksSlate,Slate,Slate,.,.,.,.,.,.,.,.,.,.,.,.,.,.,.</li>
				<li>.,.,.,.,.,.,.,.,.,ChunkSlate,.,Column_BlocksSlate_Morbid,.,Slate,Slate,Slate,Slate,Slate,Slate,Slate,Slate,Slate,Slate,Slate,Slate,Slate,.,.,.,.,.,.,.,.,.,.,.,.,.,.,.</li>
				<li>.,.,.,.,.,.,.,.,.,ChunkSlate,.,.,.,Slate,Slate,Slate,Slate,Slate,Slate,Slate,Slate,Slate,Slate,Slate,Slate,.,.,.,.,.,.,.,.,.,.,.,.,.,.,.,.</li>
				<li>.,.,.,.,.,.,.,.,.,.,.,.,.,Slate,Slate,Slate,Slate,Slate,Slate,Slate,Slate,Slate,Slate,Slate,Slate,.,.,.,.,.,.,.,.,.,.,.,.,.,.,.,.</li>
				<li>.,.,.,.,.,.,.,.,.,.,.,.,.,.,.,.,.,.,.,.,Column_BlocksSlate_Morbid,.,.,.,.,.,.,.,.,.,.,.,.,.,.,.,.,.,.,.,.</li>
			</li>
			<li>
				<li>.,.,.,.,.,.,.,.,.,.,.,.,.,.,.,.,.,.,.,.,.,.,.,.,.,.,.,.,.,.,.,.,.,.,.,.,.,.,.,.,.</li>
				<li>.,.,.,.,.,.,.,.,.,.,.,.,.,.,.,.,.,.,.,.,.,.,.,.,.,.,.,.,.,.,.,.,.,.,.,.,.,.,.,.,.</li>
				<li>.,.,.,.,.,.,.,.,.,.,.,.,.,.,.,.,.,.,.,.,.,.,.,.,.,.,.,.,.,.,.,.,.,.,.,.,.,.,.,.,.</li>
				<li>.,.,.,.,.,.,.,.,.,.,.,.,.,.,.,.,.,.,.,.,.,.,.,.,.,.,.,.,.,.,.,.,.,.,.,.,.,.,.,.,.</li>
				<li>.,.,.,.,.,.,.,.,.,.,.,.,.,.,.,.,.,.,.,.,.,.,.,.,.,.,.,.,.,.,.,.,.,.,.,.,.,.,.,.,.</li>
				<li>.,.,.,.,.,.,.,.,.,.,.,.,.,.,.,.,.,.,.,.,.,.,.,.,.,.,.,.,.,.,.,.,.,.,.,.,.,.,.,.,.</li>
				<li>.,.,.,.,.,.,.,.,.,.,.,.,.,.,.,.,.,.,.,.,.,.,.,.,.,.,.,.,.,.,.,.,.,.,.,.,.,.,.,.,.</li>
				<li>.,.,.,.,.,.,.,.,.,.,.,.,.,.,.,.,.,.,.,.,.,.,.,.,.,.,.,.,.,.,.,.,.,.,.,.,.,.,.,.,.</li>
				<li>.,.,.,.,.,.,.,.,.,.,.,.,.,.,.,.,.,.,.,.,.,.,.,.,.,.,.,.,.,.,.,.,.,.,ChunkSlate,.,.,.,.,.,.</li>
				<li>.,.,.,.,.,.,.,.,.,.,.,.,.,.,.,.,.,.,.,.,.,.,.,.,.,.,.,.,.,.,.,.,.,.,.,.,.,.,.,.,.</li>
				<li>.,.,.,.,.,.,.,.,.,.,.,.,.,.,.,.,.,.,.,Door_BlocksSlate,.,.,.,.,.,.,.,.,.,.,.,.,.,.,.,.,.,.,.,.,.</li>
				<li>.,.,.,.,.,.,.,.,.,.,.,.,.,.,.,.,.,.,.,.,.,.,.,.,.,.,.,.,.,.,.,.,.,.,.,.,.,.,.,.,.</li>
				<li>.,.,.,.,.,.,.,.,.,.,.,.,.,.,.,.,.,.,.,.,.,.,.,.,.,.,.,.,.,.,.,.,.,.,.,.,.,.,.,.,.</li>
				<li>.,.,.,.,.,.,.,.,.,.,.,.,PowerConduit,PowerConduit,PowerConduit,PowerConduit,PowerConduit,PowerConduit,PowerConduit,.,.,.,.,.,.,.,.,.,.,.,.,.,.,.,.,.,.,.,.,.,.</li>
				<li>.,.,.,.,.,.,.,.,.,.,.,.,.,.,.,.,.,.,.,.,.,.,.,.,.,.,.,.,.,.,.,.,.,.,.,.,.,.,.,.,.</li>
				<li>.,.,.,.,.,.,.,.,.,.,.,PowerConduit,VRE_HemogenPipe,.,.,.,.,.,.,.,.,.,.,.,.,.,.,.,.,.,.,.,.,.,.,.,.,.,.,.,.</li>
				<li>.,.,.,.,.,.,.,.,.,.,.,PowerConduit,VRE_HemogenPipe,.,.,.,.,.,.,.,.,.,.,.,.,.,.,.,.,.,.,.,.,.,.,.,.,.,.,.,.</li>
				<li>.,.,.,.,.,.,.,.,.,.,.,PowerConduit,.,.,.,.,.,.,.,.,.,.,.,.,.,.,.,.,.,.,.,.,.,.,.,.,.,.,.,.,.</li>
				<li>.,.,.,.,.,.,.,.,.,.,.,PowerConduit,.,.,.,.,.,.,.,.,.,.,.,.,.,.,.,.,.,.,.,.,.,.,.,.,.,.,.,.,.</li>
				<li>.,.,.,.,.,.,.,.,.,.,.,PowerConduit,PowerConduit,PowerConduit,PowerConduit,PowerConduit,PowerConduit,.,.,.,Door_BlocksSlate,.,.,.,.,.,.,.,.,.,.,.,.,.,.,.,.,.,.,.,.</li>
				<li>.,.,.,.,.,.,.,.,.,.,.,.,VRE_HemogenPipe,.,.,.,PowerConduit,.,.,.,.,.,PlantPot_BlocksSlate,.,.,.,.,.,.,.,.,.,.,.,.,.,.,.,.,.,.</li>
				<li>.,.,.,.,.,.,.,.,.,.,.,.,.,.,.,.,PowerConduit,.,.,.,.,.,.,.,.,.,.,.,.,.,.,.,.,.,.,.,.,.,.,.,.</li>
				<li>.,.,.,.,.,.,.,.,.,.,.,.,.,.,.,.,PowerConduit,.,.,.,.,.,.,.,.,.,HemogenPack,.,.,HemogenPack,.,.,.,.,.,.,.,.,.,.,.</li>
				<li>.,.,.,.,.,.,.,.,.,.,.,.,.,.,.,.,Door_BlocksSlate,.,.,.,.,.,.,.,Door_BlocksSlate,.,.,.,.,.,.,.,.,.,.,.,.,.,.,.,.</li>
				<li>.,.,.,.,.,.,.,.,.,.,.,.,.,.,.,.,PowerConduit,.,.,.,.,.,.,.,.,.,.,.,.,.,.,.,.,.,.,.,.,.,.,.,.</li>
				<li>.,.,.,.,.,.,.,.,.,.,.,.,.,.,.,.,PowerConduit,.,.,.,.,.,.,.,.,.,.,.,.,.,.,.,.,.,.,.,.,.,.,.,.</li>
				<li>.,.,.,.,.,.,.,.,.,.,.,.,.,.,.,.,PowerConduit,.,WallLamp_Morbid_North,.,.,.,.,.,.,.,Gun_AssaultRifle,.,.,HemogenPack,.,.,.,.,.,.,.,.,.,.,.</li>
				<li>.,.,.,.,.,.,.,.,.,.,.,.,.,.,.,.,PowerConduit,.,.,.,Door_BlocksSlate,.,.,.,.,.,.,.,.,.,.,.,.,.,.,.,.,.,.,.,.</li>
				<li>.,.,.,.,.,.,.,.,.,.,.,.,.,.,.,.,PowerConduit,.,.,.,.,.,.,.,.,.,.,.,.,.,.,.,.,.,.,.,.,.,.,.,.</li>
				<li>.,.,.,.,.,.,.,.,.,.,.,.,.,.,.,.,PowerConduit,.,.,.,.,.,.,.,.,.,.,.,.,.,.,.,.,.,.,.,.,.,.,.,.</li>
				<li>.,.,.,.,.,.,.,.,.,.,.,.,.,.,.,.,PowerConduit,.,.,.,.,.,.,.,.,.,.,.,.,.,.,.,.,.,.,.,.,.,.,.,.</li>
				<li>.,.,.,.,.,.,.,.,.,.,.,.,.,.,.,.,PowerConduit,.,.,.,.,.,.,.,.,.,.,.,.,.,.,.,.,.,.,.,.,.,.,.,.</li>
				<li>.,.,.,.,.,.,.,.,.,.,.,.,.,.,.,.,PowerConduit,.,.,.,.,.,.,.,.,.,.,.,.,.,.,.,.,.,.,.,.,.,.,.,.</li>
				<li>.,.,.,.,.,.,.,.,.,.,.,.,.,.,.,.,PowerConduit,.,.,.,.,.,.,.,.,.,.,.,.,.,.,.,.,.,.,.,.,.,.,.,.</li>
				<li>.,.,.,.,.,.,.,.,.,.,.,.,.,.,.,.,PowerConduit,.,.,.,.,.,.,.,.,.,.,.,.,.,.,.,.,.,.,.,.,.,.,.,.</li>
				<li>.,.,.,.,.,.,.,.,.,.,.,.,.,.,.,.,PowerConduit,.,.,.,.,.,.,.,.,.,.,.,.,.,.,.,.,.,.,.,.,.,.,.,.</li>
				<li>.,.,.,.,.,.,.,.,.,.,.,.,.,.,.,.,PowerConduit,.,.,.,.,.,.,.,.,.,.,.,.,.,.,.,.,.,.,.,.,.,.,.,.</li>
				<li>.,.,.,.,.,.,.,.,.,.,.,.,.,.,.,.,.,.,.,.,.,.,.,.,.,.,.,.,.,.,.,.,.,.,.,.,.,.,.,.,.</li>
				<li>.,.,.,.,.,.,.,.,.,.,.,.,.,.,.,.,.,.,.,.,.,.,.,.,.,.,.,.,.,.,.,.,.,.,.,.,.,.,.,.,.</li>
				<li>.,.,.,.,.,.,.,.,.,.,.,.,.,.,.,.,.,.,.,.,.,.,.,.,.,.,.,.,.,.,.,.,.,.,.,.,.,.,.,.,.</li>
				<li>.,.,.,.,.,.,.,.,.,.,.,.,.,.,.,.,.,.,.,.,.,.,.,.,.,.,.,.,.,.,.,.,.,.,.,.,.,.,.,.,.</li>
				<li>.,.,.,.,.,.,.,.,.,.,.,.,.,.,.,.,.,.,.,.,.,.,.,.,.,.,.,.,.,.,.,.,.,.,.,.,.,.,.,.,.</li>
				<li>.,.,.,.,.,.,.,.,.,.,.,.,.,.,.,.,.,.,.,.,.,.,.,.,.,.,.,.,.,.,.,.,.,.,.,.,.,.,.,.,.</li>
			</li>
			<li>
				<li>.,.,.,.,.,.,.,.,.,.,.,.,.,.,.,.,.,.,.,.,.,.,.,.,.,.,.,.,.,.,.,.,.,.,.,.,.,.,.,.,.</li>
				<li>.,.,.,.,.,.,.,.,.,.,.,.,.,.,.,.,.,.,.,.,.,.,.,.,.,.,.,.,.,.,.,.,.,.,.,.,.,.,.,.,.</li>
				<li>.,.,.,.,.,.,.,.,.,.,.,.,.,.,.,.,.,.,.,.,.,.,.,.,.,.,.,.,.,.,.,.,.,.,.,.,.,.,.,.,.</li>
				<li>.,.,.,.,.,.,.,.,.,.,.,.,.,.,.,.,.,.,.,.,.,.,.,.,.,.,.,.,.,.,.,.,.,.,.,.,.,.,.,.,.</li>
				<li>.,.,.,.,.,.,.,.,.,.,.,.,.,.,.,.,.,.,.,.,.,.,.,.,.,.,.,.,.,.,.,.,.,.,.,.,.,.,.,.,.</li>
				<li>.,.,.,.,.,.,.,.,.,.,.,.,.,.,.,.,.,.,.,.,.,.,.,.,.,.,.,.,.,.,.,.,.,.,.,.,.,.,.,.,.</li>
				<li>.,.,.,.,.,.,.,.,.,.,.,.,.,.,.,.,.,.,.,.,.,.,.,.,.,.,.,.,.,.,.,.,.,.,.,.,.,.,.,.,.</li>
				<li>.,.,.,.,.,.,.,.,.,.,.,.,.,.,.,.,.,.,.,.,.,.,.,.,.,.,.,.,.,.,.,.,.,.,.,.,.,.,.,.,.</li>
				<li>.,.,.,.,.,.,.,.,.,.,.,.,.,.,.,.,.,.,.,.,.,.,.,.,.,.,.,.,.,.,.,.,.,.,.,.,.,.,.,.,.</li>
				<li>.,.,.,.,.,.,.,.,.,.,.,.,.,.,.,.,.,.,.,.,.,.,.,.,.,.,.,.,.,.,.,.,.,.,.,.,.,.,.,.,.</li>
				<li>.,.,.,.,.,.,.,.,.,.,.,.,.,.,.,.,.,.,.,.,.,.,.,.,.,.,.,.,.,.,.,.,.,.,.,.,.,.,.,.,.</li>
				<li>.,.,.,.,.,.,.,.,.,.,.,.,.,.,.,.,.,.,.,.,.,.,.,.,.,.,.,.,.,.,.,.,.,.,.,.,.,.,.,.,.</li>
				<li>.,.,.,.,.,.,.,.,.,.,.,.,.,.,.,.,.,.,.,.,.,.,.,.,.,.,.,.,.,.,.,.,.,.,.,.,.,.,.,.,.</li>
				<li>.,.,.,.,.,.,.,.,.,.,.,.,.,.,.,.,.,.,.,.,.,.,.,.,.,.,.,.,.,.,.,.,.,.,.,.,.,.,.,.,.</li>
				<li>.,.,.,.,.,.,.,.,.,.,.,.,.,.,.,.,.,.,.,.,.,.,.,.,.,.,.,.,.,.,.,.,.,.,.,.,.,.,.,.,.</li>
				<li>.,.,.,.,.,.,.,.,.,.,.,.,.,.,.,.,.,.,.,.,.,.,.,.,.,.,.,.,.,.,.,.,.,.,.,.,.,.,.,.,.</li>
				<li>.,.,.,.,.,.,.,.,.,.,.,.,.,.,.,.,.,.,.,.,.,.,.,.,.,.,.,.,.,.,.,.,.,.,.,.,.,.,.,.,.</li>
				<li>.,.,.,.,.,.,.,.,.,.,.,.,.,.,.,.,.,.,.,.,.,.,.,.,.,.,.,.,.,.,.,.,.,.,.,.,.,.,.,.,.</li>
				<li>.,.,.,.,.,.,.,.,.,.,.,.,.,.,.,.,.,.,.,.,.,.,.,.,.,.,.,.,.,.,.,.,.,.,.,.,.,.,.,.,.</li>
				<li>.,.,.,.,.,.,.,.,.,.,.,.,VRE_HemogenPipe,.,.,.,.,.,.,.,.,.,.,.,.,.,.,.,.,.,.,.,.,.,.,.,.,.,.,.,.</li>
				<li>.,.,.,.,.,.,.,.,.,.,.,.,.,.,.,.,.,.,.,.,.,.,.,.,.,.,.,.,.,.,.,.,.,.,.,.,.,.,.,.,.</li>
				<li>.,.,.,.,.,.,.,.,.,.,.,.,.,.,.,.,.,.,.,.,.,.,.,.,.,.,.,.,.,.,.,.,.,.,.,.,.,.,.,.,.</li>
				<li>.,.,.,.,.,.,.,.,.,.,.,.,.,.,.,.,.,.,.,.,.,.,.,.,.,.,.,.,.,.,.,.,.,.,.,.,.,.,.,.,.</li>
				<li>.,.,.,.,.,.,.,.,.,.,.,.,.,.,.,.,PowerConduit,.,.,.,.,.,.,.,.,.,.,.,.,.,.,.,.,.,.,.,.,.,.,.,.</li>
				<li>.,.,.,.,.,.,.,.,.,.,.,.,.,.,.,.,.,.,.,.,.,.,.,.,.,.,.,.,.,.,.,.,.,.,.,.,.,.,.,.,.</li>
				<li>.,.,.,.,.,.,.,.,.,.,.,.,.,.,.,.,.,.,.,.,.,.,.,.,.,.,.,.,.,.,.,.,.,.,.,.,.,.,.,.,.</li>
				<li>.,.,.,.,.,.,.,.,.,.,.,.,.,.,.,.,.,.,.,.,.,.,.,.,.,.,.,.,.,.,.,.,.,.,.,.,.,.,.,.,.</li>
				<li>.,.,.,.,.,.,.,.,.,.,.,.,.,.,.,.,.,.,.,.,.,.,.,.,.,.,.,.,.,.,.,.,.,.,.,.,.,.,.,.,.</li>
				<li>.,.,.,.,.,.,.,.,.,.,.,.,.,.,.,.,.,.,.,.,.,.,.,.,.,.,.,.,.,.,.,.,.,.,.,.,.,.,.,.,.</li>
				<li>.,.,.,.,.,.,.,.,.,.,.,.,.,.,.,.,.,.,.,.,.,.,.,.,.,.,.,.,.,.,.,.,.,.,.,.,.,.,.,.,.</li>
				<li>.,.,.,.,.,.,.,.,.,.,.,.,.,.,.,.,.,.,.,.,.,.,.,.,.,.,.,.,.,.,.,.,.,.,.,.,.,.,.,.,.</li>
				<li>.,.,.,.,.,.,.,.,.,.,.,.,.,.,.,.,.,.,.,.,.,.,.,.,.,.,.,.,.,.,.,.,.,.,.,.,.,.,.,.,.</li>
				<li>.,.,.,.,.,.,.,.,.,.,.,.,.,.,.,.,.,.,.,.,.,.,.,.,.,.,.,.,.,.,.,.,.,.,.,.,.,.,.,.,.</li>
				<li>.,.,.,.,.,.,.,.,.,.,.,.,.,.,.,.,.,.,.,.,.,.,.,.,.,.,.,.,.,.,.,.,.,.,.,.,.,.,.,.,.</li>
				<li>.,.,.,.,.,.,.,.,.,.,.,.,.,.,.,.,.,.,.,.,.,.,.,.,.,.,.,.,.,.,.,.,.,.,.,.,.,.,.,.,.</li>
				<li>.,.,.,.,.,.,.,.,.,.,.,.,.,.,.,.,.,.,.,.,.,.,.,.,.,.,.,.,.,.,.,.,.,.,.,.,.,.,.,.,.</li>
				<li>.,.,.,.,.,.,.,.,.,.,.,.,.,.,.,.,.,.,.,.,.,.,.,.,.,.,.,.,.,.,.,.,.,.,.,.,.,.,.,.,.</li>
				<li>.,.,.,.,.,.,.,.,.,.,.,.,.,.,.,.,.,.,.,.,.,.,.,.,.,.,.,.,.,.,.,.,.,.,.,.,.,.,.,.,.</li>
				<li>.,.,.,.,.,.,.,.,.,.,.,.,.,.,.,.,.,.,.,.,.,.,.,.,.,.,.,.,.,.,.,.,.,.,.,.,.,.,.,.,.</li>
				<li>.,.,.,.,.,.,.,.,.,.,.,.,.,.,.,.,.,.,.,.,.,.,.,.,.,.,.,.,.,.,.,.,.,.,.,.,.,.,.,.,.</li>
				<li>.,.,.,.,.,.,.,.,.,.,.,.,.,.,.,.,.,.,.,.,.,.,.,.,.,.,.,.,.,.,.,.,.,.,.,.,.,.,.,.,.</li>
				<li>.,.,.,.,.,.,.,.,.,.,.,.,.,.,.,.,.,.,.,.,.,.,.,.,.,.,.,.,.,.,.,.,.,.,.,.,.,.,.,.,.</li>
				<li>.,.,.,.,.,.,.,.,.,.,.,.,.,.,.,.,.,.,.,.,.,.,.,.,.,.,.,.,.,.,.,.,.,.,.,.,.,.,.,.,.</li>
			</li>
		</layouts>
		<roofGrid>
			<li>.,.,.,.,.,.,.,.,.,.,.,.,.,.,.,.,.,.,.,.,.,.,.,.,.,.,.,.,.,.,.,.,.,.,.,.,.,.,.,.,.</li>
			<li>.,.,.,.,.,.,.,.,.,.,.,.,.,.,.,.,.,.,.,.,.,.,.,.,.,.,.,.,.,.,.,.,.,.,.,.,.,.,.,.,.</li>
			<li>.,.,.,.,.,.,.,.,.,.,.,.,.,.,.,.,.,.,.,.,.,.,.,.,.,.,.,.,.,.,.,.,.,.,.,.,.,.,.,.,.</li>
			<li>.,.,.,.,.,.,.,.,.,.,.,.,.,.,.,.,.,.,.,.,.,.,.,.,.,.,.,.,.,.,.,.,.,.,.,.,.,.,.,.,.</li>
			<li>.,.,.,.,.,.,.,.,.,.,.,.,.,.,.,.,.,.,.,.,.,.,.,.,.,.,.,.,.,.,.,.,.,.,.,.,.,.,.,.,.</li>
			<li>.,.,.,.,.,.,.,.,.,.,.,.,.,.,.,.,.,.,.,.,.,.,.,.,.,.,.,.,.,.,.,.,.,.,.,.,.,.,.,.,.</li>
			<li>.,.,.,.,.,.,.,.,.,.,.,.,.,.,.,.,.,.,.,.,.,.,.,.,.,.,.,.,.,.,.,.,.,.,.,.,.,.,.,.,.</li>
			<li>.,.,.,.,.,.,.,.,.,.,.,.,.,.,.,.,.,.,.,.,.,.,.,.,.,.,.,.,.,.,.,.,.,.,.,.,.,.,.,.,.</li>
			<li>.,.,.,.,.,.,.,.,.,.,.,.,.,.,.,.,.,.,.,.,.,.,.,.,.,.,.,.,.,.,.,.,.,.,.,.,.,.,.,.,.</li>
			<li>.,.,.,.,.,.,.,.,.,.,.,.,.,.,.,.,.,.,.,3,3,3,.,.,.,.,.,.,.,.,.,.,.,.,.,.,.,.,.,.,.</li>
			<li>.,.,.,.,.,.,.,.,.,.,.,.,.,.,.,.,.,.,.,3,3,3,.,.,.,.,.,.,.,.,.,.,.,.,.,.,.,.,.,.,.</li>
			<li>.,.,.,.,.,.,.,.,.,.,.,.,.,.,.,.,.,.,.,3,3,3,.,.,.,.,.,.,.,.,.,.,.,.,.,.,.,.,.,.,.</li>
			<li>.,.,.,.,.,.,.,.,.,.,.,.,.,.,.,3,3,3,3,3,3,3,3,3,3,3,.,.,.,.,.,.,.,.,.,.,.,.,.,.,.</li>
			<li>.,.,.,.,.,.,.,.,.,.,.,.,.,.,.,3,3,3,3,3,3,3,3,3,3,3,.,.,.,.,.,.,.,.,.,.,.,.,.,.,.</li>
			<li>.,.,.,.,.,.,.,.,.,.,3,3,3,3,3,3,3,3,3,3,3,3,3,3,3,3,3,3,3,3,3,3,.,.,.,.,.,.,.,.,.</li>
			<li>.,.,.,.,.,.,.,.,.,.,3,3,3,3,3,3,3,3,3,3,3,3,3,3,3,3,3,3,3,3,3,3,.,.,.,.,.,.,.,.,.</li>
			<li>.,.,.,.,.,.,.,.,.,.,3,3,3,3,3,3,3,3,3,3,3,3,3,3,3,3,3,3,3,3,3,3,.,.,.,.,.,.,.,.,.</li>
			<li>.,.,.,.,.,.,.,.,.,.,3,3,3,3,3,3,3,3,3,3,3,3,3,3,3,3,3,3,3,3,3,3,.,.,.,.,.,.,.,.,.</li>
			<li>.,.,.,.,.,.,.,.,.,.,3,3,3,3,3,3,3,3,3,3,3,3,3,3,3,3,3,3,3,3,3,3,.,.,.,.,.,.,.,.,.</li>
			<li>.,.,.,.,.,.,.,.,.,.,3,3,3,3,3,3,3,3,3,3,3,3,3,3,3,3,3,3,3,3,3,3,.,.,.,.,.,.,.,.,.</li>
			<li>.,.,.,.,.,.,.,.,.,.,3,3,3,3,3,3,3,3,3,3,3,3,3,3,3,3,3,3,3,3,3,3,.,.,.,.,.,.,.,.,.</li>
			<li>.,.,.,.,.,.,.,.,.,.,3,3,3,3,3,3,3,3,3,3,3,3,3,3,3,3,3,3,3,3,3,3,.,.,.,.,.,.,.,.,.</li>
			<li>.,.,.,.,.,.,.,.,.,.,3,3,3,3,3,3,3,3,3,3,3,3,3,3,3,3,3,3,3,3,3,3,.,.,.,.,.,.,.,.,.</li>
			<li>.,.,.,.,.,.,.,.,.,.,3,3,3,3,3,3,3,3,3,3,3,3,3,3,3,3,3,3,3,3,3,3,.,.,.,.,.,.,.,.,.</li>
			<li>.,.,.,.,.,.,.,.,.,.,3,3,3,3,3,3,3,3,3,3,3,3,3,3,3,3,3,3,3,3,3,3,.,.,.,.,.,.,.,.,.</li>
			<li>.,.,.,.,.,.,.,.,.,.,3,3,3,3,3,3,3,3,3,3,3,3,3,3,3,3,3,3,3,3,3,3,.,.,.,.,.,.,.,.,.</li>
			<li>.,.,.,.,.,.,.,.,.,.,3,3,3,3,3,3,3,3,3,3,3,3,3,3,3,3,3,3,3,3,3,3,.,.,.,.,.,.,.,.,.</li>
			<li>.,.,.,.,.,.,.,.,.,.,.,.,.,.,.,3,3,3,3,3,3,3,3,3,3,3,.,.,.,.,.,.,.,.,.,.,.,.,.,.,.</li>
			<li>.,.,.,.,.,.,.,.,.,.,.,.,.,.,.,3,3,3,3,3,3,3,3,3,3,3,.,.,.,.,.,.,.,.,.,.,.,.,.,.,.</li>
			<li>.,.,.,.,.,.,.,.,.,.,.,.,.,.,.,3,3,3,3,3,3,3,3,3,3,3,.,.,.,.,.,.,.,.,.,.,.,.,.,.,.</li>
			<li>.,.,.,.,.,.,.,.,.,.,.,.,.,.,.,3,3,3,3,3,3,3,3,3,3,3,.,.,.,.,.,.,.,.,.,.,.,.,.,.,.</li>
			<li>.,.,.,.,.,.,.,.,.,.,.,.,.,.,.,3,3,3,3,3,3,3,3,3,3,3,.,.,.,.,.,.,.,.,.,.,.,.,.,.,.</li>
			<li>.,.,.,.,.,.,.,.,.,.,.,.,.,.,.,3,3,3,3,3,3,3,3,3,3,3,.,.,.,.,.,.,.,.,.,.,.,.,.,.,.</li>
			<li>.,.,.,.,.,.,.,.,.,.,.,.,.,.,.,3,3,3,3,3,3,3,3,3,3,3,.,.,.,.,.,.,.,.,.,.,.,.,.,.,.</li>
			<li>.,.,.,.,.,.,.,.,.,.,.,.,.,.,.,3,3,3,3,3,3,3,3,3,3,3,.,.,.,.,.,.,.,.,.,.,.,.,.,.,.</li>
			<li>.,.,.,.,.,.,.,.,.,.,.,.,.,.,.,3,3,3,3,3,3,3,3,3,3,3,.,.,.,.,.,.,.,.,.,.,.,.,.,.,.</li>
			<li>.,.,.,.,.,.,.,.,.,.,.,.,.,.,.,3,3,3,3,3,3,3,3,3,3,3,.,.,.,.,.,.,.,.,.,.,.,.,.,.,.</li>
			<li>.,.,.,.,.,.,.,.,.,.,.,.,.,.,.,3,3,3,3,3,3,3,3,3,3,3,.,.,.,.,.,.,.,.,.,.,.,.,.,.,.</li>
			<li>.,.,.,.,.,.,.,.,.,.,.,.,.,.,.,.,.,.,.,.,.,.,.,.,.,.,.,.,.,.,.,.,.,.,.,.,.,.,.,.,.</li>
			<li>.,.,.,.,.,.,.,.,.,.,.,.,.,.,.,.,.,.,.,.,.,.,.,.,.,.,.,.,.,.,.,.,.,.,.,.,.,.,.,.,.</li>
			<li>.,.,.,.,.,.,.,.,.,.,.,.,.,.,.,.,.,.,.,.,.,.,.,.,.,.,.,.,.,.,.,.,.,.,.,.,.,.,.,.,.</li>
			<li>.,.,.,.,.,.,.,.,.,.,.,.,.,.,.,.,.,.,.,.,.,.,.,.,.,.,.,.,.,.,.,.,.,.,.,.,.,.,.,.,.</li>
			<li>.,.,.,.,.,.,.,.,.,.,.,.,.,.,.,.,.,.,.,.,.,.,.,.,.,.,.,.,.,.,.,.,.,.,.,.,.,.,.,.,.</li>
		</roofGrid>
		<terrainGrid>
			<li>.,.,.,.,.,.,.,.,.,.,.,.,.,.,.,.,.,.,.,.,.,.,.,.,.,.,.,.,.,.,.,.,.,.,.,.,.,.,.,.,.</li>
			<li>.,.,.,.,.,.,.,.,.,.,.,.,.,.,.,.,.,.,.,.,.,.,.,.,.,.,.,.,.,.,.,.,.,.,.,.,.,.,.,.,.</li>
			<li>.,.,.,.,.,.,.,.,.,.,.,.,.,.,.,.,.,.,.,.,.,.,.,.,.,.,.,.,.,Slate_RoughHewn,Slate_RoughHewn,Slate_RoughHewn,Slate_RoughHewn,.,.,.,.,.,.,.,.</li>
			<li>.,.,.,.,.,.,.,.,.,.,.,.,.,.,.,.,.,.,.,.,.,.,.,.,.,.,.,.,.,.,.,.,.,.,.,.,.,.,.,.,.</li>
			<li>.,.,.,.,.,.,.,.,.,.,.,.,.,.,.,.,.,.,.,.,Slate_RoughHewn,.,.,.,.,Slate_RoughHewn,Slate_RoughHewn,.,.,.,.,.,.,.,.,.,.,.,.,.,.</li>
			<li>.,.,.,.,.,.,.,.,.,.,.,.,.,.,.,.,.,.,Slate_RoughHewn,Slate_RoughHewn,Slate_RoughHewn,.,.,.,.,.,.,.,.,.,.,.,.,.,.,.,.,.,.,.,.</li>
			<li>.,.,.,.,.,.,.,.,.,.,.,.,.,.,.,.,.,.,.,.,.,.,.,Slate_RoughHewn,Slate_RoughHewn,Slate_RoughHewn,.,.,.,Slate_RoughHewn,.,.,.,.,.,.,.,.,.,.,.</li>
			<li>.,.,.,.,.,.,.,.,.,.,.,.,.,.,.,.,.,.,.,.,.,.,.,.,.,.,.,.,.,Slate_RoughHewn,.,.,.,.,.,.,.,.,.,.,.</li>
			<li>.,.,.,.,.,Slate_RoughHewn,.,.,.,.,.,.,.,.,.,.,.,.,.,.,.,.,.,Slate_RoughHewn,Slate_RoughHewn,Slate_RoughHewn,.,Slate_RoughHewn,Slate_RoughHewn,Slate_RoughHewn,.,.,.,.,.,.,.,.,.,.,.</li>
			<li>.,.,.,.,.,.,.,.,.,.,.,.,.,.,.,.,.,.,.,.,.,.,.,Slate_RoughHewn,Slate_RoughHewn,Slate_RoughHewn,.,Slate_RoughHewn,Slate_RoughHewn,.,.,.,.,.,.,.,.,.,.,.,.</li>
			<li>.,.,.,.,.,.,.,.,.,.,.,.,.,.,.,.,.,.,Slate_RoughHewn,Slate_RoughHewn,Slate_RoughHewn,.,.,Slate_RoughHewn,Slate_RoughHewn,Slate_RoughHewn,.,Slate_RoughHewn,Slate_RoughHewn,.,.,.,.,.,.,.,.,.,.,.,.</li>
			<li>.,.,.,.,.,.,.,.,.,.,Slate_RoughHewn,.,.,.,.,.,.,.,.,.,Slate_RoughHewn,.,.,Slate_RoughHewn,Slate_RoughHewn,Slate_RoughHewn,.,.,Slate_RoughHewn,.,.,.,.,.,Slate_RoughHewn,.,.,.,.,.,.</li>
			<li>.,.,.,.,.,.,.,.,.,Slate_RoughHewn,Slate_RoughHewn,Slate_RoughHewn,.,.,Slate_RoughHewn,Slate_RoughHewn,.,.,.,.,Slate_RoughHewn,Slate_RoughHewn,Slate_RoughHewn,Slate_RoughHewn,Slate_RoughHewn,Slate_RoughHewn,.,.,Slate_RoughHewn,.,.,.,.,.,Slate_RoughHewn,.,.,.,.,.,.</li>
			<li>.,.,.,.,.,.,.,.,.,Slate_RoughHewn,Slate_RoughHewn,Slate_RoughHewn,.,.,.,.,.,.,.,.,Slate_RoughHewn,.,.,Slate_RoughHewn,Slate_RoughHewn,Slate_RoughHewn,.,.,.,.,.,.,.,.,.,.,.,.,.,.,.</li>
			<li>.,.,.,.,.,.,.,.,.,Slate_RoughHewn,Slate_RoughHewn,Slate_RoughHewn,Tile_MorbidSlate,Tile_MorbidSlate,Tile_MorbidSlate,Tile_MorbidSlate,Tile_MorbidSlate,Tile_MorbidSlate,Tile_MorbidSlate,Slate_RoughHewn,Slate_RoughHewn,Slate_RoughHewn,Tile_MorbidSlate,Tile_MorbidSlate,Tile_MorbidSlate,Tile_MorbidSlate,Tile_MorbidSlate,Tile_MorbidSlate,.,.,.,.,.,.,.,.,.,.,.,.,.</li>
			<li>.,.,.,.,.,.,.,.,.,.,Slate_RoughHewn,Slate_RoughHewn,Tile_MorbidSlate,Tile_MorbidSlate,Tile_MorbidSlate,Tile_MorbidSlate,Tile_MorbidSlate,Tile_MorbidSlate,Tile_MorbidSlate,Slate_RoughHewn,Slate_RoughHewn,Slate_RoughHewn,Tile_MorbidSlate,Tile_MorbidSlate,Tile_MorbidSlate,Tile_MorbidSlate,Tile_MorbidSlate,Tile_MorbidSlate,Slate_RoughHewn,.,.,.,.,.,.,.,.,.,.,.,.</li>
			<li>.,.,.,Slate_RoughHewn,Slate_RoughHewn,.,.,.,.,Slate_RoughHewn,Slate_RoughHewn,Slate_RoughHewn,Tile_MorbidSlate,Tile_MorbidSlate,Tile_MorbidSlate,Tile_MorbidSlate,Tile_MorbidSlate,Tile_MorbidSlate,Tile_MorbidSlate,Slate_RoughHewn,Slate_RoughHewn,Slate_RoughHewn,Tile_MorbidSlate,Tile_MorbidSlate,Tile_MorbidSlate,Tile_MorbidSlate,Tile_MorbidSlate,Tile_MorbidSlate,.,.,.,.,.,.,.,.,.,.,.,.,.</li>
			<li>.,.,.,Slate_RoughHewn,Slate_RoughHewn,.,.,.,.,Slate_RoughHewn,Slate_RoughHewn,Slate_RoughHewn,Tile_MorbidSlate,Tile_MorbidSlate,Tile_MorbidSlate,Tile_MorbidSlate,Tile_MorbidSlate,Tile_MorbidSlate,Tile_MorbidSlate,Slate_RoughHewn,Slate_RoughHewn,Slate_RoughHewn,Tile_MorbidSlate,Tile_MorbidSlate,Tile_MorbidSlate,Tile_MorbidSlate,Tile_MorbidSlate,Tile_MorbidSlate,.,.,.,.,.,.,.,.,.,.,Slate_RoughHewn,Slate_RoughHewn,.</li>
			<li>.,.,.,.,.,.,.,.,.,.,Slate_RoughHewn,Slate_RoughHewn,Tile_MorbidSlate,Tile_MorbidSlate,Tile_MorbidSlate,Tile_MorbidSlate,Tile_MorbidSlate,Tile_MorbidSlate,Tile_MorbidSlate,PavedTile,Slate_RoughHewn,PavedTile,Tile_MorbidSlate,Tile_MorbidSlate,Tile_MorbidSlate,Tile_MorbidSlate,Tile_MorbidSlate,Tile_MorbidSlate,Slate_RoughHewn,Slate_RoughHewn,Slate_RoughHewn,Slate_RoughHewn,Slate_RoughHewn,Slate_RoughHewn,.,.,.,.,.,.,.</li>
			<li>.,.,.,.,.,.,.,.,.,.,Slate_RoughHewn,Slate_RoughHewn,Slate_RoughHewn,Slate_RoughHewn,Slate_RoughHewn,PavedTile,PavedTile,PavedTile,PavedTile,PavedTile,PavedTile,PavedTile,PavedTile,PavedTile,PavedTile,PavedTile,Slate_RoughHewn,Slate_RoughHewn,Slate_RoughHewn,Slate_RoughHewn,Slate_RoughHewn,Slate_RoughHewn,Slate_RoughHewn,Slate_RoughHewn,.,.,.,.,.,.,.</li>
			<li>.,.,.,.,.,.,.,.,.,.,Tile_MorbidSlate,Tile_MorbidSlate,Tile_MorbidSlate,Tile_MorbidSlate,Tile_MorbidSlate,PavedTile,PavedTile,PavedTile,PavedTile,PavedTile,PavedTile,PavedTile,PavedTile,PavedTile,PavedTile,Tile_MorbidSlate,Tile_MorbidSlate,Tile_MorbidSlate,Tile_MorbidSlate,Tile_MorbidSlate,Tile_MorbidSlate,Tile_MorbidSlate,Slate_RoughHewn,Slate_RoughHewn,.,.,.,.,.,.,.</li>
			<li>.,.,.,.,.,.,.,.,.,.,Tile_MorbidSlate,Tile_MorbidSlate,Tile_MorbidSlate,Tile_MorbidSlate,Tile_MorbidSlate,PavedTile,PavedTile,PavedTile,PavedTile,PavedTile,PavedTile,PavedTile,PavedTile,PavedTile,PavedTile,Tile_MorbidSlate,Tile_MorbidSlate,Tile_MorbidSlate,Tile_MorbidSlate,Tile_MorbidSlate,Tile_MorbidSlate,Tile_MorbidSlate,.,.,.,.,.,.,.,.,.</li>
			<li>.,.,.,Slate_RoughHewn,.,.,.,.,.,.,Tile_MorbidSlate,Tile_MorbidSlate,Tile_MorbidSlate,Tile_MorbidSlate,Tile_MorbidSlate,PavedTile,PavedTile,PavedTile,PavedTile,PavedTile,PavedTile,PavedTile,PavedTile,PavedTile,PavedTile,Tile_MorbidSlate,Tile_MorbidSlate,Tile_MorbidSlate,Tile_MorbidSlate,Tile_MorbidSlate,Tile_MorbidSlate,Tile_MorbidSlate,.,.,.,.,.,.,.,.,.</li>
			<li>.,.,.,.,.,.,.,.,.,.,Tile_MorbidSlate,Tile_MorbidSlate,Tile_MorbidSlate,Tile_MorbidSlate,Tile_MorbidSlate,Slate_RoughHewn,PavedTile,PavedTile,PavedTile,PavedTile,PavedTile,PavedTile,PavedTile,PavedTile,PavedTile,Tile_MorbidSlate,Tile_MorbidSlate,Tile_MorbidSlate,Tile_MorbidSlate,Tile_MorbidSlate,Tile_MorbidSlate,Tile_MorbidSlate,.,.,.,.,.,.,.,.,.</li>
			<li>.,.,.,.,.,Slate_RoughHewn,Slate_RoughHewn,.,.,Slate_RoughHewn,Tile_MorbidSlate,Tile_MorbidSlate,Tile_MorbidSlate,Tile_MorbidSlate,Tile_MorbidSlate,PavedTile,PavedTile,PavedTile,PavedTile,PavedTile,PavedTile,PavedTile,PavedTile,PavedTile,PavedTile,Tile_MorbidSlate,Tile_MorbidSlate,Tile_MorbidSlate,Tile_MorbidSlate,Tile_MorbidSlate,Tile_MorbidSlate,Tile_MorbidSlate,.,.,.,.,.,.,.,.,.</li>
			<li>.,.,.,.,.,Slate_RoughHewn,Slate_RoughHewn,Slate_RoughHewn,.,Slate_RoughHewn,Tile_MorbidSlate,Tile_MorbidSlate,Tile_MorbidSlate,Tile_MorbidSlate,Tile_MorbidSlate,PavedTile,PavedTile,PavedTile,PavedTile,PavedTile,PavedTile,PavedTile,PavedTile,PavedTile,PavedTile,Tile_MorbidSlate,Tile_MorbidSlate,Tile_MorbidSlate,Tile_MorbidSlate,Tile_MorbidSlate,Tile_MorbidSlate,Tile_MorbidSlate,.,.,.,.,.,.,.,.,.</li>
			<li>.,.,.,.,.,Slate_RoughHewn,Slate_RoughHewn,Slate_RoughHewn,.,Slate_RoughHewn,Tile_MorbidSlate,Tile_MorbidSlate,Tile_MorbidSlate,Tile_MorbidSlate,Tile_MorbidSlate,PavedTile,PavedTile,PavedTile,PavedTile,PavedTile,PavedTile,PavedTile,PavedTile,PavedTile,PavedTile,Tile_MorbidSlate,Tile_MorbidSlate,Tile_MorbidSlate,Tile_MorbidSlate,Tile_MorbidSlate,Tile_MorbidSlate,Tile_MorbidSlate,Slate_RoughHewn,Slate_RoughHewn,.,.,.,.,.,.,.</li>
			<li>.,.,.,.,.,.,.,Slate_RoughHewn,.,Slate_RoughHewn,Slate_RoughHewn,Slate_RoughHewn,Slate_RoughHewn,Slate_RoughHewn,Slate_RoughHewn,PavedTile,PavedTile,PavedTile,PavedTile,PavedTile,PavedTile,PavedTile,PavedTile,PavedTile,PavedTile,PavedTile,Slate_RoughHewn,.,Slate_RoughHewn,Slate_RoughHewn,Slate_RoughHewn,Slate_RoughHewn,Slate_RoughHewn,Slate_RoughHewn,.,.,.,.,.,.,.</li>
			<li>.,.,.,.,.,.,.,.,.,.,Slate_RoughHewn,Slate_RoughHewn,Slate_RoughHewn,Slate_RoughHewn,Slate_RoughHewn,PavedTile,PavedTile,Tile_MorbidSlate,Tile_MorbidSlate,Tile_MorbidSlate,Tile_MorbidSlate,Tile_MorbidSlate,Tile_MorbidSlate,Tile_MorbidSlate,PavedTile,PavedTile,Slate_RoughHewn,.,Slate_RoughHewn,Slate_RoughHewn,Slate_RoughHewn,Slate_RoughHewn,Slate_RoughHewn,Slate_RoughHewn,.,.,.,.,.,.,.</li>
			<li>.,.,.,.,.,.,.,.,.,.,Slate_RoughHewn,Slate_RoughHewn,Slate_RoughHewn,Slate_RoughHewn,Slate_RoughHewn,Slate_RoughHewn,Slate_RoughHewn,Tile_MorbidSlate,Tile_MorbidSlate,CarpetScarlet,CarpetScarlet,CarpetScarlet,Tile_MorbidSlate,Tile_MorbidSlate,Slate_RoughHewn,Slate_RoughHewn,Slate_RoughHewn,.,Slate_RoughHewn,Slate_RoughHewn,Slate_RoughHewn,Slate_RoughHewn,.,.,.,.,.,.,.,.,.</li>
			<li>.,.,.,.,.,.,.,.,.,.,.,Slate_RoughHewn,Slate_RoughHewn,Slate_RoughHewn,Slate_RoughHewn,Slate_RoughHewn,Slate_RoughHewn,CarpetScarlet,CarpetScarlet,CarpetScarlet,CarpetScarlet,CarpetScarlet,CarpetScarlet,CarpetScarlet,Slate_RoughHewn,Slate_RoughHewn,Slate_RoughHewn,.,Slate_RoughHewn,Slate_RoughHewn,Slate_RoughHewn,Slate_RoughHewn,.,.,.,.,.,.,.,.,.</li>
			<li>.,.,.,.,.,.,.,.,.,.,Slate_RoughHewn,Slate_RoughHewn,Slate_RoughHewn,Slate_RoughHewn,Slate_RoughHewn,Slate_RoughHewn,Slate_RoughHewn,Tile_MorbidSlate,Tile_MorbidSlate,CarpetScarlet,CarpetScarlet,CarpetScarlet,Tile_MorbidSlate,Tile_MorbidSlate,Slate_RoughHewn,.,.,.,Slate_RoughHewn,Slate_RoughHewn,Slate_RoughHewn,Slate_RoughHewn,.,.,.,.,.,.,.,.,.</li>
			<li>.,.,.,.,.,.,.,.,.,.,.,Slate_RoughHewn,Slate_RoughHewn,Slate_RoughHewn,.,.,.,CarpetScarlet,CarpetScarlet,CarpetScarlet,CarpetScarlet,CarpetScarlet,CarpetScarlet,CarpetScarlet,.,.,.,.,Slate_RoughHewn,Slate_RoughHewn,Slate_RoughHewn,Slate_RoughHewn,.,.,.,.,.,.,.,.,.</li>
			<li>.,.,.,.,.,.,.,.,.,.,.,Slate_RoughHewn,Slate_RoughHewn,Slate_RoughHewn,.,.,Slate_RoughHewn,Tile_MorbidSlate,Tile_MorbidSlate,CarpetScarlet,CarpetScarlet,CarpetScarlet,Tile_MorbidSlate,Tile_MorbidSlate,.,.,.,.,Slate_RoughHewn,Slate_RoughHewn,Slate_RoughHewn,Slate_RoughHewn,.,.,.,.,.,.,.,.,.</li>
			<li>.,.,.,.,.,Slate_RoughHewn,Slate_RoughHewn,Slate_RoughHewn,Slate_RoughHewn,.,.,.,.,.,.,.,.,CarpetScarlet,CarpetScarlet,CarpetScarlet,CarpetScarlet,CarpetScarlet,CarpetScarlet,CarpetScarlet,.,.,.,.,.,.,.,.,.,.,.,.,.,.,.,.,.</li>
			<li>.,.,.,.,.,Slate_RoughHewn,Slate_RoughHewn,Slate_RoughHewn,Slate_RoughHewn,Slate_RoughHewn,Slate_RoughHewn,.,.,Slate_RoughHewn,.,.,.,Tile_MorbidSlate,Tile_MorbidSlate,CarpetScarlet,CarpetScarlet,CarpetScarlet,Tile_MorbidSlate,Tile_MorbidSlate,.,.,.,.,.,.,.,.,.,.,.,.,.,.,.,.,.</li>
			<li>.,.,.,.,.,Slate_RoughHewn,Slate_RoughHewn,Slate_RoughHewn,Slate_RoughHewn,Slate_RoughHewn,Slate_RoughHewn,Slate_RoughHewn,Slate_RoughHewn,Slate_RoughHewn,.,.,.,Tile_MorbidSlate,Tile_MorbidSlate,Tile_MorbidSlate,Tile_MorbidSlate,Tile_MorbidSlate,Tile_MorbidSlate,Tile_MorbidSlate,.,.,.,.,Slate_RoughHewn,Slate_RoughHewn,.,.,.,.,.,.,.,.,.,.,.</li>
			<li>.,.,.,.,.,Slate_RoughHewn,Slate_RoughHewn,Slate_RoughHewn,.,Slate_RoughHewn,Slate_RoughHewn,Slate_RoughHewn,Slate_RoughHewn,Slate_RoughHewn,.,.,.,.,.,.,.,.,.,.,Slate_RoughHewn,Slate_RoughHewn,.,.,.,.,.,.,.,.,.,.,.,.,.,.,.</li>
			<li>.,.,.,.,.,.,.,.,.,.,.,.,.,.,.,.,.,.,.,.,.,.,.,.,.,.,.,.,.,.,.,.,.,.,.,.,.,.,.,.,.</li>
			<li>.,.,.,.,.,.,.,.,.,.,.,.,.,.,.,.,Slate_RoughHewn,Slate_RoughHewn,Slate_RoughHewn,.,.,.,.,.,Slate_RoughHewn,.,.,.,.,.,.,.,.,.,.,.,.,.,.,.,.</li>
			<li>.,.,.,.,.,.,.,.,.,.,.,.,.,.,.,.,.,.,.,.,.,.,.,.,.,.,.,.,.,.,.,.,.,.,.,.,.,.,.,.,.</li>
			<li>.,.,.,.,.,.,.,.,.,.,.,.,.,.,.,.,.,.,.,.,.,.,.,.,.,.,.,.,.,.,.,.,.,.,.,.,.,.,.,.,.</li>
			<li>.,.,.,.,.,.,.,.,.,.,.,.,.,.,.,.,.,.,.,.,.,.,.,.,.,.,.,.,.,.,.,Granite_RoughHewn,.,.,Granite_RoughHewn,.,.,.,.,.,.</li>
		</terrainGrid>
		<terrainColorGrid>
			<li>.,.,.,.,.,.,.,.,.,.,.,.,.,.,.,.,.,.,.,.,.,.,.,.,.,.,.,.,.,.,.,.,.,.,.,.,.,.,.,.,.</li>
			<li>.,.,.,.,.,.,.,.,.,.,.,.,.,.,.,.,.,.,.,.,.,.,.,.,.,.,.,.,.,.,.,.,.,.,.,.,.,.,.,.,.</li>
			<li>.,.,.,.,.,.,.,.,.,.,.,.,.,.,.,.,.,.,.,.,.,.,.,.,.,.,.,.,.,.,.,.,.,.,.,.,.,.,.,.,.</li>
			<li>.,.,.,.,.,.,.,.,.,.,.,.,.,.,.,.,.,.,.,.,.,.,.,.,.,.,.,.,.,.,.,.,.,.,.,.,.,.,.,.,.</li>
			<li>.,.,.,.,.,.,.,.,.,.,.,.,.,.,.,.,.,.,.,.,.,.,.,.,.,.,.,.,.,.,.,.,.,.,.,.,.,.,.,.,.</li>
			<li>.,.,.,.,.,.,.,.,.,.,.,.,.,.,.,.,.,.,.,.,.,.,.,.,.,.,.,.,.,.,.,.,.,.,.,.,.,.,.,.,.</li>
			<li>.,.,.,.,.,.,.,.,.,.,.,.,.,.,.,.,.,.,.,.,.,.,.,.,.,.,.,.,.,.,.,.,.,.,.,.,.,.,.,.,.</li>
			<li>.,.,.,.,.,.,.,.,.,.,.,.,.,.,.,.,.,.,.,.,.,.,.,.,.,.,.,.,.,.,.,.,.,.,.,.,.,.,.,.,.</li>
			<li>.,.,.,.,.,.,.,.,.,.,.,.,.,.,.,.,.,.,.,.,.,.,.,.,.,.,.,.,.,.,.,.,.,.,.,.,.,.,.,.,.</li>
			<li>.,.,.,.,.,.,.,.,.,.,.,.,.,.,.,.,.,.,.,.,.,.,.,.,.,.,.,.,.,.,.,.,.,.,.,.,.,.,.,.,.</li>
			<li>.,.,.,.,.,.,.,.,.,.,.,.,.,.,.,.,.,.,.,.,.,.,.,.,.,.,.,.,.,.,.,.,.,.,.,.,.,.,.,.,.</li>
			<li>.,.,.,.,.,.,.,.,.,.,.,.,.,.,.,.,.,.,.,.,.,.,.,.,.,.,.,.,.,.,.,.,.,.,.,.,.,.,.,.,.</li>
			<li>.,.,.,.,.,.,.,.,.,.,.,.,.,.,.,.,.,.,.,.,.,.,.,.,.,.,.,.,.,.,.,.,.,.,.,.,.,.,.,.,.</li>
			<li>.,.,.,.,.,.,.,.,.,.,.,.,.,.,.,.,.,.,.,.,.,.,.,.,.,.,.,.,.,.,.,.,.,.,.,.,.,.,.,.,.</li>
			<li>.,.,.,.,.,.,.,.,.,.,.,.,.,.,.,.,.,.,.,.,.,.,.,.,.,.,.,.,.,.,.,.,.,.,.,.,.,.,.,.,.</li>
			<li>.,.,.,.,.,.,.,.,.,.,.,.,.,.,.,.,.,.,.,.,.,.,.,.,.,.,.,.,.,.,.,.,.,.,.,.,.,.,.,.,.</li>
			<li>.,.,.,.,.,.,.,.,.,.,.,.,.,.,.,.,.,.,.,.,.,.,.,.,.,.,.,.,.,.,.,.,.,.,.,.,.,.,.,.,.</li>
			<li>.,.,.,.,.,.,.,.,.,.,.,.,.,.,.,.,.,.,.,.,.,.,.,.,.,.,.,.,.,.,.,.,.,.,.,.,.,.,.,.,.</li>
			<li>.,.,.,.,.,.,.,.,.,.,.,.,.,.,.,.,.,.,.,.,.,.,.,.,.,.,.,.,.,.,.,.,.,.,.,.,.,.,.,.,.</li>
			<li>.,.,.,.,.,.,.,.,.,.,.,.,.,.,.,.,.,.,.,.,Structure_Black,.,.,.,.,.,.,.,.,.,.,.,.,.,.,.,.,.,.,.,.</li>
			<li>.,.,.,.,.,.,.,.,.,.,.,.,.,.,.,.,.,.,Structure_Black,Structure_Black,Structure_Black,Structure_Black,Structure_Black,.,.,.,.,.,.,.,.,.,.,.,.,.,.,.,.,.,.</li>
			<li>.,.,.,.,.,.,.,.,.,.,.,.,.,.,.,.,.,Structure_Black,Structure_Black,Structure_Black,Structure_Black,Structure_Black,Structure_Black,Structure_Black,.,.,.,.,.,.,.,.,.,.,.,.,.,.,.,.,.</li>
			<li>.,.,.,.,.,.,.,.,.,.,.,.,.,.,.,.,.,Structure_Black,Structure_Black,Structure_Black,Structure_Black,Structure_Black,Structure_Black,Structure_Black,.,.,.,.,.,.,.,.,.,.,.,.,.,.,.,.,.</li>
			<li>.,.,.,.,.,.,.,.,.,.,.,.,.,.,.,.,Structure_Black,Structure_Black,Structure_Black,Structure_Black,Structure_Black,Structure_Black,Structure_Black,Structure_Black,Structure_Black,.,.,.,.,.,.,.,.,.,.,.,.,.,.,.,.</li>
			<li>.,.,.,.,.,.,.,.,.,.,.,.,.,.,.,.,.,Structure_Black,Structure_Black,Structure_Black,Structure_Black,Structure_Black,Structure_Black,Structure_Black,.,.,.,.,.,.,.,.,.,.,.,.,.,.,.,.,.</li>
			<li>.,.,.,.,.,.,.,.,.,.,.,.,.,.,.,.,.,Structure_Black,Structure_Black,Structure_Black,Structure_Black,Structure_Black,Structure_Black,Structure_Black,.,.,.,.,.,.,.,.,.,.,.,.,.,.,.,.,.</li>
			<li>.,.,.,.,.,.,.,.,.,.,.,.,.,.,.,.,.,.,Structure_Black,Structure_Black,Structure_Black,Structure_Black,Structure_Black,.,.,.,.,.,.,.,.,.,.,.,.,.,.,.,.,.,.</li>
			<li>.,.,.,.,.,.,.,.,.,.,.,.,.,.,.,.,.,.,.,.,Structure_Black,.,.,.,.,.,.,.,.,.,.,.,.,.,.,.,.,.,.,.,.</li>
			<li>.,.,.,.,.,.,.,.,.,.,.,.,.,.,.,.,.,.,.,.,.,.,.,.,.,.,.,.,.,.,.,.,.,.,.,.,.,.,.,.,.</li>
			<li>.,.,.,.,.,.,.,.,.,.,.,.,.,.,.,.,.,.,.,.,.,.,.,.,.,.,.,.,.,.,.,.,.,.,.,.,.,.,.,.,.</li>
			<li>.,.,.,.,.,.,.,.,.,.,.,.,.,.,.,.,.,.,.,.,.,.,.,.,.,.,.,.,.,.,.,.,.,.,.,.,.,.,.,.,.</li>
			<li>.,.,.,.,.,.,.,.,.,.,.,.,.,.,.,.,.,.,.,.,.,.,.,.,.,.,.,.,.,.,.,.,.,.,.,.,.,.,.,.,.</li>
			<li>.,.,.,.,.,.,.,.,.,.,.,.,.,.,.,.,.,.,.,.,.,.,.,.,.,.,.,.,.,.,.,.,.,.,.,.,.,.,.,.,.</li>
			<li>.,.,.,.,.,.,.,.,.,.,.,.,.,.,.,.,.,.,.,.,.,.,.,.,.,.,.,.,.,.,.,.,.,.,.,.,.,.,.,.,.</li>
			<li>.,.,.,.,.,.,.,.,.,.,.,.,.,.,.,.,.,.,.,.,.,.,.,.,.,.,.,.,.,.,.,.,.,.,.,.,.,.,.,.,.</li>
			<li>.,.,.,.,.,.,.,.,.,.,.,.,.,.,.,.,.,.,.,.,.,.,.,.,.,.,.,.,.,.,.,.,.,.,.,.,.,.,.,.,.</li>
			<li>.,.,.,.,.,.,.,.,.,.,.,.,.,.,.,.,.,.,.,.,.,.,.,.,.,.,.,.,.,.,.,.,.,.,.,.,.,.,.,.,.</li>
			<li>.,.,.,.,.,.,.,.,.,.,.,.,.,.,.,.,.,.,.,.,.,.,.,.,.,.,.,.,.,.,.,.,.,.,.,.,.,.,.,.,.</li>
			<li>.,.,.,.,.,.,.,.,.,.,.,.,.,.,.,.,.,.,.,.,.,.,.,.,.,.,.,.,.,.,.,.,.,.,.,.,.,.,.,.,.</li>
			<li>.,.,.,.,.,.,.,.,.,.,.,.,.,.,.,.,.,.,.,.,.,.,.,.,.,.,.,.,.,.,.,.,.,.,.,.,.,.,.,.,.</li>
			<li>.,.,.,.,.,.,.,.,.,.,.,.,.,.,.,.,.,.,.,.,.,.,.,.,.,.,.,.,.,.,.,.,.,.,.,.,.,.,.,.,.</li>
			<li>.,.,.,.,.,.,.,.,.,.,.,.,.,.,.,.,.,.,.,.,.,.,.,.,.,.,.,.,.,.,.,.,.,.,.,.,.,.,.,.,.</li>
			<li>.,.,.,.,.,.,.,.,.,.,.,.,.,.,.,.,.,.,.,.,.,.,.,.,.,.,.,.,.,.,.,.,.,.,.,.,.,.,.,.,.</li>
		</terrainColorGrid>
		<modRequirements>
			<li>ludeon.rimworld.ideology</li>
			<li>vanillaracesexpanded.sanguophage</li>
			<li>sarg.alphagenes</li>
			<li>ludeon.rimworld.biotech</li>
			<li>sarg.alphamemes</li>
			<li>ludeon.rimworld.royalty</li>
		</modRequirements>
	</KCSG.StructureLayoutDef>
</Defs>